cpuf.v
// LITTLE ENDIAN
// First four bytes are instruction, last four address
// verilator lint_off BLKANDNBLK

// INSTRUCTIONS
// [_ _ _ _][_ _ _ _]
//   Instr.   Addr.
// OP_LDA : 1000 => Load value at address into register A
// OP_LDB : 0100 => Load value at address into register B
// OP_ADD : 0010 => Add values in Register A and bus and dump in register B
// OP_SUB : 0001 => Subtract value in  bus from register A
// OP_MUL : 1100 => Mutiply A and value in bus and dump in register B
// OP_DIV : 1010 => Divide A by value in bus and dump in register B
// OP_JMP : 1001 => Jump to instruction at address
// OP_HLT : 1111 => Halt 

// STUFF ON Instruction Bus
module program_counter(inout [7:0] bus_i, input clk, input reset, input pc_a);
    
    reg [3:0] pc;
    
    always @(posedge clk) begin
        if (reset)
            pc <= 0;
        else if (pc_a)
            pc <= pc + 1; 
    end

    assign bus_i = (pc_a) ? {4'bz,pc} : 8'bz;

endmodule

module instruction_register(inout [7:0] bus_i, input [7:0] from_ram, output [3:0] to_ctrl, output [3:0] to_ram, input clk, input reset, input ir_a);

    reg [3:0] instruction;
    reg [3:0] address; // Address in instruction

    always @(posedge clk) begin
        if (reset)
            instruction <= 0;
        else if (ir_a)
            instruction <= from_ram[7:4]; 
        address <= from_ram[3:0];
    end

    //assign bus_i = (out_b) ? {instruction,4'bz} : 8'bz;
    assign to_ctrl = (ir_a) ? instruction : 4'bz;
    assign to_ram = address;

endmodule

module mar(inout [7:0] bus_i, output [3:0] to_ram, input [3:0] from_ir, input clk, input reset, input mar_a);

    reg [3:0] address;

    always @(posedge clk) begin
        if(reset)
            address <= 0;
        else if (mar_a)
            address <= bus_i[3:0];
        else
            address <= from_ir;
    end

    //assign to_ram = (mar_a) ? address : 4'bz;
    assign to_ram = address;
endmodule
// -----

// RAM
module ram(output [7:0] to_ir, inout [7:0] to_a, inout [7:0] to_b, input [3:0] mar_in, input [3:0] address_ir, input in_b, input out_b, input in_a, input out_a, input clk, input reset);

    reg [128:0] mem;
    reg [7:0] index;
    reg [7:0] out;

    always @(posedge clk) begin
        mem[7:0] <= 8'b10000011;
        mem[15:8] <= 8'b10000001;
        mem[23:16] <= 8'b01101111;
        mem[31:24] <= 8'b00000010;
        mem[39:32] <= 8'b00000001;
        mem[47:40] <= 8'b00001001;
        
        if(reset) begin
            index <= 0;
            out <= 0;
        end
        else if(in_b) begin
            mem[127:120] <= to_b;
        end
        else if(in_a) begin
            mem[119:112] <= to_a;
        end
        index <= mar_in * 8;
        //index <= address_ir*8;
        out <= mem[index +: 8];
    end

    assign to_a = (out_a) ? out : 8'bz;
    assign to_b = (out_b) ? out : 8'bz;
    assign to_ir = out;

endmodule
// Stuff on data bus

module register(inout [7:0] bus_d, input [7:0] from_ram, input clk, input ram_in, input out_b);

    reg [7:0] areg;

    always @(posedge clk) begin
        if (ram_in)
            areg <= from_ram;
    end

    assign bus_d = (out_b) ? areg : 8'bz;


endmodule


module alu(inout [7:0] bus_d, input [7:0] from_a, output [7:0] to_b, input ad, input sub);
    reg [7:0] out;
    
    always @(posedge clk) begin
        if(ad)
            out <= from_a + bus_d;
        if(sub)
            out <= from_a - bus_d;
    
    assign to_b = (ad || sub) ? out : 8'bz;

    end

endmodule

module controller(inout [7:0] bus_i, inout [7:0] bus_d, output reg pc_a, output reg mar_a, output reg ir_a, output reg in_a, output reg out_a, input [3:0] ir_i, input clk, input reset);
    reg [2:0] stagecount = 0;
    reg aflag = 0;

    // CODES

    parameter OP_LDA = 4'b1000;
    parameter OP_LDB = 4'b0100;
    parameter OP_ADD = 4'b0010;
    parameter OP_SUB = 4'b0001;
    parameter OP_MUL = 4'b1100;
    parameter OP_DIV = 4'b1010;
    parameter OP_JMP = 4'b1001;
    parameter OP_HLT = 4'b1111;


    // Control word: pc_a, mar_a, ir_a, in_a, out_a

    always @(posedge clk) begin
        stagecount = stagecount + 1;
        if (stagecount == 6) begin
            pc_a = 0;
            mar_a = 0;
            ir_a = 0;
            in_a = 0;
            out_a = 0;
            //ctrl_wd = 000;
            stagecount = 0;
        end
        // First 3 stages are always the same
        if (stagecount == 1) begin
            pc_a = 1;
            mar_a = 1;
            ir_a = 0;
            in_a = 0;
            out_a = 0;
            //ctrl_wd = 110;
        end
        if (stagecount == 2) begin
            pc_a = 0;
            mar_a = 1;
            ir_a = 0;
            in_a = 0;
            out_a = 0;
            //ctrl_wd = 010;
        end
        if (stagecount == 3) begin
            pc_a = 0;
            mar_a = 0;
            ir_a = 1;
            in_a = 0;
            out_a = 0;
            //ctrl_wd = 001;
        end
        if (ir_i == OP_LDA) begin
            if (stagecount == 4) begin
                pc_a = 0;
                mar_a = 0;
                ir_a = 0;
                in_a = 0;
                out_a = 1;
            end
            if (stagecount == 5) begin
                pc_a = 0;
                mar_a = 0;
                ir_a = 0;
                in_a = 0;
                out_a = 0;
            end
        end 


        
    end


endmodule

module top(output [7:0] bus_i, input clk, input reset);
    reg pc_a = 0;
    reg mar_a = 0;
    reg ir_a = 0;
    // RAM flags
    reg in_b = 0;
    reg out_b = 0;
    reg in_a = 0;
    reg out_a = 0;
    //-----
    // Register flags
    reg a_out = 0;
    //----
    reg out_bus = 0;
    reg [3:0] ir_i;
    reg [7:0] bus_d;
    wire [3:0] to_ram;
    wire [7:0] to_ir;
    wire [7:0] to_a;
    wire [7:0] to_b;
    wire [3:0] address_ir;

    controller control(.bus_i(bus_i), .bus_d(bus_d), .pc_a(pc_a), .mar_a(mar_a), .ir_a(ir_a), .in_a(in_a), .out_a(out_a), .ir_i(ir_i), .clk(clk), .reset(reset));

    program_counter counter(.bus_i(bus_i), .clk(clk), .reset(reset), .pc_a(pc_a));

    mar mar(.bus_i(bus_i), .to_ram(to_ram), .from_ir(address_ir), .clk(clk), .reset(reset), .mar_a(mar_a));

    ram ram(.to_ir(to_ir), .to_a(to_a), .to_b(to_b), .mar_in(to_ram), .address_ir(address_ir), .in_b(in_b), .out_b(out_b), .in_a(in_a), .out_a(out_a), .clk(clk), .reset(reset));

    instruction_register ir(.bus_i(bus_i), .from_ram(to_ir), .to_ctrl(ir_i), .to_ram(address_ir), .clk(clk), .reset(reset), .ir_a(ir_a));

    register areg(.bus_d(bus_d), .from_ram(to_a), .clk(clk), .ram_in(out_a), .out_b(a_out));




endmodule

Waveform.vcd
$version Generated by VerilatedVcd $end
$timescale 1ps $end

 $scope module TOP $end
  $var wire  8 7 bus_i [7:0] $end
  $var wire  1 8 clk $end
  $var wire  1 9 reset $end
  $scope module top $end
   $var wire  1 : a_out $end
   $var wire  4 , address_ir [3:0] $end
   $var wire  8 ; bus_d [7:0] $end
   $var wire  8 7 bus_i [7:0] $end
   $var wire  1 8 clk $end
   $var wire  1 & in_a $end
   $var wire  1 : in_b $end
   $var wire  1 % ir_a $end
   $var wire  4 ( ir_i [3:0] $end
   $var wire  1 $ mar_a $end
   $var wire  1 ' out_a $end
   $var wire  1 : out_b $end
   $var wire  1 : out_bus $end
   $var wire  1 # pc_a $end
   $var wire  1 9 reset $end
   $var wire  8 + to_a [7:0] $end
   $var wire  8 ; to_b [7:0] $end
   $var wire  8 * to_ir [7:0] $end
   $var wire  4 ) to_ram [3:0] $end
   $scope module areg $end
    $var wire  8 - areg [7:0] $end
    $var wire  8 ; bus_d [7:0] $end
    $var wire  1 8 clk $end
    $var wire  8 + from_ram [7:0] $end
    $var wire  1 : out_b $end
    $var wire  1 ' ram_in $end
   $upscope $end
   $scope module control $end
    $var wire  4 > OP_ADD [3:0] $end
    $var wire  4 A OP_DIV [3:0] $end
    $var wire  4 C OP_HLT [3:0] $end
    $var wire  4 B OP_JMP [3:0] $end
    $var wire  4 < OP_LDA [3:0] $end
    $var wire  4 = OP_LDB [3:0] $end
    $var wire  4 @ OP_MUL [3:0] $end
    $var wire  4 ? OP_SUB [3:0] $end
    $var wire  1 : aflag $end
    $var wire  8 ; bus_d [7:0] $end
    $var wire  8 7 bus_i [7:0] $end
    $var wire  1 8 clk $end
    $var wire  1 & in_a $end
    $var wire  1 % ir_a $end
    $var wire  4 ( ir_i [3:0] $end
    $var wire  1 $ mar_a $end
    $var wire  1 ' out_a $end
    $var wire  1 # pc_a $end
    $var wire  1 9 reset $end
    $var wire  3 . stagecount [2:0] $end
   $upscope $end
   $scope module counter $end
    $var wire  8 7 bus_i [7:0] $end
    $var wire  1 8 clk $end
    $var wire  4 / pc [3:0] $end
    $var wire  1 # pc_a $end
    $var wire  1 9 reset $end
   $upscope $end
   $scope module ir $end
    $var wire  4 , address [3:0] $end
    $var wire  8 7 bus_i [7:0] $end
    $var wire  1 8 clk $end
    $var wire  8 * from_ram [7:0] $end
    $var wire  4 0 instruction [3:0] $end
    $var wire  1 % ir_a $end
    $var wire  1 9 reset $end
    $var wire  4 ( to_ctrl [3:0] $end
    $var wire  4 , to_ram [3:0] $end
   $upscope $end
   $scope module mar $end
    $var wire  4 ) address [3:0] $end
    $var wire  8 7 bus_i [7:0] $end
    $var wire  1 8 clk $end
    $var wire  4 , from_ir [3:0] $end
    $var wire  1 $ mar_a $end
    $var wire  1 9 reset $end
    $var wire  4 ) to_ram [3:0] $end
   $upscope $end
   $scope module ram $end
    $var wire  4 , address_ir [3:0] $end
    $var wire  1 8 clk $end
    $var wire  1 & in_a $end
    $var wire  1 : in_b $end
    $var wire  8 6 index [7:0] $end
    $var wire  4 ) mar_in [3:0] $end
    $var wire 129 1 mem [128:0] $end
    $var wire  8 * out [7:0] $end
    $var wire  1 ' out_a $end
    $var wire  1 : out_b $end
    $var wire  1 9 reset $end
    $var wire  8 + to_a [7:0] $end
    $var wire  8 ; to_b [7:0] $end
    $var wire  8 * to_ir [7:0] $end
   $upscope $end
  $upscope $end
 $upscope $end
$enddefinitions $end


#0
0#
0$
0%
0&
0'
b0000 (
b0000 )
b00000000 *
b00000000 +
b0000 ,
b00000000 -
b000 .
b0000 /
b0000 0
b000000000000000000000000000000000000000000000000000000000000000000000000000000000000000000000000000000000000000000000000000000000 1
b00000000 6
b00000000 7
18
09
0:
b00000000 ;
b1000 <
b0100 =
b0010 >
b0001 ?
b1100 @
b1010 A
b1001 B
b1111 C
#1
08
#2
1#
1$
b001 .
b0001 /
b000000000000000000000000000000000000000000000000000000000000000000000000000000000000010010000000100000010011011111000000110000011 1
b00000001 7
18
#3
08
#4
0#
b0001 )
b10000011 *
b010 .
b00000000 7
18
#5
08
#6
0$
1%
b1000 (
b0000 )
b0011 ,
b011 .
b1000 0
b00001000 6
18
#7
08
#8
0%
1'
b0000 (
b0011 )
b10000001 *
b10000001 +
b100 .
b00000000 6
18
#9
08
#10
b10000011 *
b10000011 +
b0001 ,
b10000001 -
b101 .
b00011000 6
18
#11
08
#12
0'
b0001 )
b00000010 *
b00000000 +
b0011 ,
b000 .
18
#13
08
#14
1#
1$
b0000 )
b0010 ,
b001 .
b0010 /
b00001000 6
b00000010 7
18
#15
08
#16
0#
b0010 )
b10000001 *
b010 .
b00000000 6
b00000000 7
18
#17
08
#18
0$
1%
b1000 (
b10000011 *
b0001 ,
b011 .
b00010000 6
18
#19
08
#20
0%
1'
b0000 (
b0001 )
b01101111 *
b01101111 +
b0011 ,
b00000000 -
b100 .
18
#21
08
#22
b0011 )
b1111 ,
b01101111 -
b101 .
b00001000 6
18
#23
08
#24
0'
b1111 )
b10000001 *
b00000000 +
b000 .
b00011000 6
18
#25
08
#26
1#
1$
b0000 )
b00000010 *
b0001 ,
b001 .
b0011 /
b01111000 6
b00000011 7
18
#27
08
#28
0#
b0011 )
b00000000 *
b0010 ,
b010 .
b00000000 6
b00000000 7
18
#29
08
#30
0$
1%
b0010 )
b10000011 *
b0000 ,
b011 .
b0000 0
b00011000 6
18
#31
08
#32
b1000 (
b0000 )
b00000010 *
b0011 ,
b100 .
b1000 0
b00010000 6
18
#33
08
#34
0%
b0000 (
b0011 )
b01101111 *
b0010 ,
b101 .
b00000000 6
18
#35
08
#36
b0010 )
b10000011 *
b1111 ,
b000 .
b00011000 6
18
#37
08
#38
1#
1$
b0000 )
b00000010 *
b0011 ,
b001 .
b0100 /
b00010000 6
b00000100 7
18
#39
08
#40
0#
b0100 )
b01101111 *
b0010 ,
b010 .
b00000000 6
b00000000 7
18
#41
08
#42
0$
1%
b0110 (
b0010 )
b10000011 *
b1111 ,
b011 .
b0110 0
b00100000 6
18
#43
08
#44
b1000 (
b1111 )
b00000001 *
b0011 ,
b100 .
b1000 0
b00010000 6
18
#45
08
#46
0%
b0000 (
b0011 )
b01101111 *
b0001 ,
b101 .
b01111000 6
18
#47
08
#48
b0001 )
b00000000 *
b1111 ,
b000 .
b00011000 6
18
#49
08
#50
1#
1$
b0000 )
b00000010 *
b0000 ,
b001 .
b0101 /
b00001000 6
b00000101 7
18
#51
08
#52
0#
b0101 )
b10000001 *
b0010 ,
b010 .
b00000000 6
b00000000 7
18
#53
08
#54
0$
1%
b1000 (
b0010 )
b10000011 *
b0001 ,
b011 .
b00101000 6
18
#55
08
#56
0%
1'
b0000 (
b0001 )
b00001001 *
b00001001 +
b0011 ,
b00000000 -
b100 .
b00010000 6
18
#57
08
#58
b0011 )
b01101111 *
b01101111 +
b1001 ,
b00001001 -
b101 .
b00001000 6
18
#59
08
#60
0'
b1001 )
b10000001 *
b00000000 +
b1111 ,
b000 .
b00011000 6
18
#61
08
#62
1#
1$
b0000 )
b00000010 *
b0001 ,
b001 .
b0110 /
b01001000 6
b00000110 7
18
#63
08
#64
0#
b0110 )
b00000000 *
b0010 ,
b010 .
b00000000 6
b00000000 7
18
#65
08
#66
0$
1%
b0010 )
b10000011 *
b0000 ,
b011 .
b0000 0
b00110000 6
18
#67
08
#68
b1000 (
b0000 )
b00000000 *
b0011 ,
b100 .
b1000 0
b00010000 6
18
#69
08
#70
0%
b0000 (
b0011 )
b01101111 *
b0000 ,
b101 .
b00000000 6
18
#71
08
#72
b0000 )
b10000011 *
b1111 ,
b000 .
b00011000 6
18
#73
08
#74
1#
1$
b00000010 *
b0011 ,
b001 .
b0111 /
b00000000 6
b00000111 7
18
#75
08
#76
0#
b0111 )
b10000011 *
b0010 ,
b010 .
b00000000 7
18
#77
08
#78
0$
1%
b1000 (
b0010 )
b0011 ,
b011 .
b00111000 6
18
#79
08
#80
0%
1'
b0000 (
b0011 )
b00000000 *
b00000000 -
b100 .
b00010000 6
18
#81
08
#82
b01101111 *
b01101111 +
b0000 ,
b101 .
b00011000 6
18
#83
08
#84
0'
b0000 )
b00000010 *
b00000000 +
b1111 ,
b000 .
18
#85
08
#86
1#
1$
b0010 ,
b001 .
b1000 /
b00000000 6
b00001000 7
18
#87
08
#88
0#
b1000 )
b10000011 *
b010 .
b00000000 7
18
#89
08
#90
0$
1%
b1000 (
b0010 )
b0011 ,
b011 .
b01000000 6
18
#91
08
#92
0%
1'
b0000 (
b0011 )
b00000000 *
b100 .
b00010000 6
18
#93
08
#94
b01101111 *
b01101111 +
b0000 ,
b101 .
b00011000 6
18
#95
08
#96
0'
b0000 )
b00000010 *
b00000000 +
b1111 ,
b000 .
18
#97
08
#98
1#
1$
b0010 ,
b001 .
b1001 /
b00000000 6
b00001001 7
18
