cpuf.v
// LITTLE ENDIAN
// First four bytes are instruction, last four address
// verilator lint_off BLKANDNBLK

// INSTRUCTIONS
// [_ _ _ _][_ _ _ _]
//   Instr.   Addr.
// OP_LDA : 1000 => Load value at address into register A
// OP_LDB : 0100 => Load value at address into register B
// OP_ADD : 0010 => Add values in Register A and B and dump in accumulator
// OP_SUB : 0001 => Subtract value in B from register A and dump in accumulator
// OP_JMP : 1001 => Jump to instruction at address
// OP_HLT : 1111 => Halt 
// OP_WRT : 1010 => Write accumulator contents to RAM

// STUFF ON Instruction Bus
module program_counter(inout [7:0] bus_i, input clk, input reset, input pc_a, input [3:0] from_ir, input jmp);
    
    reg [3:0] pc;
    
    always @(posedge clk) begin
        if (reset)
            pc <= 0;
        else if (pc_a)
            pc <= pc + 1; 
        else if (jmp)
            pc <= from_ir - 4'b0001;
    end

    assign bus_i = (pc_a) ? {4'bz,pc} : 8'bz;

endmodule

module instruction_register(inout [7:0] bus_i, input [7:0] from_ram, output [3:0] to_ctrl, output [3:0] to_ram, input clk, input reset, input ir_a);

    reg [3:0] instruction;
    reg [3:0] address; // Address in instruction

    always @(posedge clk) begin
        if (reset) begin
            instruction <= 0;
        end
        else if (ir_a) begin
            address <= from_ram[3:0];
            instruction <= from_ram[7:4];
        end 
    end

    //assign bus_i = (out_b) ? {instruction,4'bz} : 8'bz;
    assign to_ctrl = (1) ? instruction : 4'bz;
    assign to_ram = address;

endmodule

module mar(inout [7:0] bus_i, output [3:0] to_ram, input [3:0] from_ir, input clk, input reset, input mar_a, input jmp);

    reg [3:0] address;
    reg [3:0] offset;

    always @(posedge clk) begin
        if (mar_a) begin
            address <= bus_i[3:0];
        end
        else if (jmp) begin
            address <= from_ir;
            
        end
        //else
        //    address <= from_ir;
    end

    //assign to_ram = (mar_a) ? address : 4'bz;
    assign to_ram = address;
endmodule
// -----

// RAM
module ram(output [7:0] to_ir, inout [7:0] to_a, inout [7:0] to_b, inout [7:0] to_c, input [3:0] mar_in, input [3:0] address_ir, input in_c, input in_b, input out_b, input in_a, input out_a, input clk, input reset);

    reg [128:0] mem;
    reg [7:0] index_ir;
    reg [7:0] index_reg;
    reg [7:0] out_reg;
    reg [7:0] out_ir;

    always @(posedge clk) begin
        mem[7:0] <= 8'b00000100;
        mem[15:8] <= 8'b10000110; //LDA 0110
        mem[23:16] <= 8'b01000101; //LDB 0111
        mem[31:24] <= 8'b00100001; //ADD
        mem[39:32] <= 8'b10010111; //JMP 0111
        mem[47:40] <= 8'b00001110;
        mem[55:48] <= 8'b00001100;
        mem[63:56] <= 8'b10000110; //LDA 0101
        mem[71:64] <= 8'b10000110; //LDA 0110
        mem[79:72] <= 8'b10100110; //WRT
        mem[87:80] <= 8'b10001111; //LDA 1000
        mem[95:88] <= 8'b11111111; //HLT
        
        if(reset) begin
            //index <= 0;
            //out <= 0;
        end
        else if(in_c) begin
            mem[127:120] <= to_c;
        end
        else if(in_a) begin
            mem[119:112] <= to_a;
        end


        index_ir <= mar_in * 8;
        out_ir <= mem[index_ir +: 8];

        index_reg <= out_ir[3:0] * 8;
        out_reg <= mem[index_reg +: 8];

    end

    assign to_a = (out_a) ? out_reg : 8'bz;
    assign to_b = (out_b) ? out_reg : 8'bz;
    assign to_ir = out_ir;

endmodule
// Stuff on data bus

module register(output [7:0] to_out, inout [7:0] bus_d, input [7:0] from_inp, input clk, input inp_in, input out_o, input out_b);

    reg [7:0] areg;

    always @(negedge clk) begin
        if (inp_in)
            areg <= from_inp;
    end

    assign bus_d = (out_b) ? areg : 8'bz;
    assign to_out = areg;


endmodule

module alu(output reg [7:0] to_acc, inout [7:0] bus_d, input [7:0] from_a, input [7:0] from_b, input clk, input ad, input sub);
    reg [7:0] out;
    
    always @(posedge clk) begin
        if(ad)
            out <= from_a + from_b;
        if(sub)
            out <= from_a - from_b;
    
    assign to_acc = (1) ? out : 8'bz; //ad || sub

    end

endmodule

module controller(inout [7:0] bus_i, inout [7:0] bus_d, output reg pc_a, output reg mar_a, output reg ir_a, output reg in_a, output reg out_a, output reg in_b, output reg out_b, output reg ad, output reg sb, output reg jmp, output reg acc_out, input [3:0] ir_i, input clk, input reset);
    reg [2:0] stagecount = 0;
    reg aflag = 0;

    // CODES

    parameter OP_LDA = 4'b1000;
    parameter OP_LDB = 4'b0100;
    parameter OP_ADD = 4'b0010;
    parameter OP_SUB = 4'b0001;
    parameter OP_MUL = 4'b1100;
    parameter OP_DIV = 4'b1010;
    parameter OP_JMP = 4'b1001;
    parameter OP_HLT = 4'b1111;
    parameter OP_WRT = 4'b1010;


    // Control word: pc_a, mar_a, ir_a, in_a (input to ram), out_a (output from ram), in_b, out_b, ad, sb, jmp, acc_out

    always @(posedge clk) begin
        if (ir_i == OP_HLT) begin
            pc_a = 0;
            mar_a = 0;
            ir_a = 0;
            in_a = 0;
            out_a = 0;
            in_b = 0;
            out_b = 0;
            ad = 0;
            sb = 0;
            jmp = 0;
        end
        else begin
            stagecount = stagecount + 1;
            if (stagecount == 6) begin
                pc_a = 0;
                mar_a = 0;
                ir_a = 0;
                in_a = 0;
                out_a = 0;
                in_b = 0;
                out_b = 0;
                ad = 0;
                sb = 0;
                jmp = 0;
                acc_out = 0;
                //ctrl_wd = 000;
                stagecount = 0;
            end
            // First 3 stages are always the same
            if (stagecount == 1) begin
                pc_a = 1;
                mar_a = 0; //0
                ir_a = 0; //0
                in_a = 0;
                out_a = 0;
                in_b = 0;
                out_b = 0;
                ad = 0;
                sb = 0;
                jmp = 0;
                acc_out = 0;
                //ctrl_wd = 110;
            end
            if (stagecount == 2) begin
                pc_a = 0;
                mar_a = 1;
                ir_a = 0; //0
                in_a = 0;
                out_a = 0;
                in_b = 0;
                out_b = 0;
                jmp = 0;
                acc_out = 0;
                //ctrl_wd = 010;
            end
            if (stagecount == 3) begin
                pc_a = 0;
                mar_a = 0;
                ir_a = 1; //1
                in_a = 0;
                out_a = 0;
                in_b = 0;
                out_b = 0;
                ad = 0;
                sb = 0;
                jmp = 0;
                acc_out = 0;
                //ctrl_wd = 001;
            end
            if (ir_i == OP_JMP) begin
                if (stagecount == 4) begin
                    pc_a = 0;
                    mar_a = 0;
                    ir_a = 0;
                    in_a = 0;
                    out_a = 0;
                    in_b = 0;
                    out_b = 0;
                    ad = 0;
                    sb = 0;
                    jmp = 1;
                    acc_out = 0;
                end
                if (stagecount == 5) begin
                    pc_a = 0;
                    mar_a = 0;
                    ir_a = 0;
                    in_a = 0;
                    out_a = 0;
                    in_b = 0;
                    out_b = 0;
                    ad = 0;
                    sb = 0;
                    jmp = 0;
                    acc_out = 0;
                end

            end
            else begin
                if (ir_i == OP_LDA) begin
                    if (stagecount == 4) begin
                        pc_a = 0;
                        mar_a = 0;
                        ir_a = 0;
                        in_a = 0;
                        out_a = 1;
                        in_b = 0;
                        out_b = 0;
                        ad = 0;
                        sb = 0;
                        jmp = 0;
                        acc_out = 0;
                    end
                    if (stagecount == 5) begin
                        pc_a = 0;
                        mar_a = 0;
                        ir_a = 0;
                        in_a = 0;
                        out_a = 0;
                        in_b = 0;
                        out_b = 0;
                        ad = 0;
                        sb = 0;
                        jmp = 0;
                        acc_out = 0;
                    end
                end 
                else if (ir_i == OP_LDB) begin
                    if (stagecount == 4) begin
                        pc_a = 0;
                        mar_a = 0;
                        ir_a = 0;
                        in_a = 0;
                        out_a = 0;
                        in_b = 0;
                        out_b = 1;
                        ad = 0;
                        sb = 0;
                        jmp = 0;
                        acc_out = 0;
                    end
                    if (stagecount == 5) begin
                        pc_a = 0;
                        mar_a = 0;
                        ir_a = 0;
                        in_a = 0;
                        out_a = 0;
                        in_b = 0;
                        out_b = 0;
                        ad = 0;
                        sb = 0;
                        jmp = 0;
                        acc_out = 0;
                    end
                end
                else if (ir_i == OP_ADD) begin
                    if (stagecount == 4) begin
                        pc_a = 0;
                        mar_a = 0;
                        ir_a = 0;
                        in_a = 0;
                        out_a = 0;
                        in_b = 0;
                        out_b = 0;
                        ad = 1;
                        sb = 0;
                        jmp = 0;
                        acc_out = 0;
                    end
                    if (stagecount == 5) begin
                        pc_a = 0;
                        mar_a = 0;
                        ir_a = 0;
                        in_a = 0;
                        out_a = 0;
                        in_b = 0;
                        out_b = 0;
                        ad = 0;
                        sb = 0;
                        jmp = 0;
                        acc_out = 0;
                    end
                end
                else if (ir_i == OP_SUB) begin
                    if (stagecount == 4) begin
                        pc_a = 0;
                        mar_a = 0;
                        ir_a = 0;
                        in_a = 0;
                        out_a = 0;
                        in_b = 0;
                        out_b = 0;
                        ad = 0;
                        sb = 1;
                        jmp = 0;
                        acc_out = 0;
                    end
                    if (stagecount == 5) begin
                        pc_a = 0;
                        mar_a = 0;
                        ir_a = 0;
                        in_a = 0;
                        out_a = 0;
                        in_b = 0;
                        out_b = 0;
                        ad = 0;
                        sb = 0;
                        jmp = 0;
                        acc_out = 0;
                    end
                end
                else if (ir_i == OP_WRT) begin
                    if (stagecount == 4) begin
                        pc_a = 0;
                        mar_a = 0;
                        ir_a = 0;
                        in_a = 0;
                        out_a = 0;
                        in_b = 0;
                        out_b = 0;
                        ad = 0;
                        sb = 0;
                        jmp = 0;
                        acc_out = 1;
                    end
                    if (stagecount == 5) begin
                        pc_a = 0;
                        mar_a = 0;
                        ir_a = 0;
                        in_a = 0;
                        out_a = 0;
                        in_b = 0;
                        out_b = 0;
                        ad = 0;
                        sb = 0;
                        jmp = 0;
                        acc_out = 0;
                    end
                end

                else begin
                    if (stagecount == 4) begin
                        pc_a = 0;
                        mar_a = 0;
                        ir_a = 0;
                        in_a = 0;
                        out_a = 0;
                        in_b = 0;
                        out_b = 0;
                        ad = 0;
                        sb = 0;
                        jmp = 0;
                        acc_out = 0;
                    end
                    if (stagecount == 5) begin
                        pc_a = 0;
                        mar_a = 0;
                        ir_a = 0;
                        in_a = 0;
                        out_a = 0;
                        in_b = 0;
                        out_b = 0;
                        ad = 0;
                        sb = 0;
                        jmp = 0;
                        acc_out = 0;
                    end
                end
            end
        end
    end
endmodule

module top(output [7:0] bus_i, input clk, input reset);
    reg pc_a = 0;
    reg mar_a = 0;
    reg ir_a = 0;
    reg jmp = 0;
    // RAM flags
    reg in_b = 0;
    reg out_b = 0;
    reg in_a = 0;
    reg out_a = 0;
    //-----
    // accumulator
    reg c_out_acc = 1; //calculator out
    reg acc_out = 0;
    reg ad = 0;
    reg sb = 0;
    // Register flags (BUS OUT)
    reg a_out = 0;
    reg b_out = 0;
    //----
    reg out_bus = 0;
    reg [3:0] ir_i;
    reg [7:0] bus_d;
    wire [3:0] to_ram;
    wire [7:0] to_ir;
    wire [7:0] to_a;
    wire [7:0] to_b;
    wire [7:0] to_acc;
    wire [7:0] a_calc;
    wire [7:0] b_calc;
    wire [7:0] c_calc;
    wire [3:0] address_ir;

    controller control(.bus_i(bus_i), .bus_d(bus_d), .pc_a(pc_a), .mar_a(mar_a), .ir_a(ir_a), .in_a(in_a), .out_a(out_a), .in_b(in_b), .out_b(out_b), .ad(ad), .sb(sb), .jmp(jmp), .acc_out(acc_out), .ir_i(ir_i), .clk(clk), .reset(reset));

    program_counter counter(.bus_i(bus_i), .clk(clk), .reset(reset), .pc_a(pc_a), .from_ir(address_ir), .jmp(jmp));

    mar mar(.bus_i(bus_i), .to_ram(to_ram), .from_ir(address_ir), .clk(clk), .reset(reset), .mar_a(mar_a), .jmp(jmp));

    ram ram(.to_ir(to_ir), .to_a(to_a), .to_b(to_b), .to_c(c_calc), .mar_in(to_ram), .address_ir(address_ir), .in_c(acc_out), .in_b(in_b), .out_b(out_b), .in_a(in_a), .out_a(out_a), .clk(clk), .reset(reset));

    instruction_register ir(.bus_i(bus_i), .from_ram(to_ir), .to_ctrl(ir_i), .to_ram(address_ir), .clk(clk), .reset(reset), .ir_a(ir_a));

    register areg(.to_out(a_calc), .bus_d(bus_d), .from_inp(to_a), .clk(clk), .inp_in(out_a), .out_o(0), .out_b(a_out));
    
    //register breg(.to_c(b_calc), .bus_d(bus_d), .from_ram(to_b), .clk(clk), .ram_in(out_b), .out_b(b_out));
    register breg(.to_out(b_calc), .bus_d(bus_d), .from_inp(to_b), .clk(clk), .inp_in(out_b), .out_o(0), .out_b(b_out));

    register accumulator(.to_out(c_calc), .bus_d(bus_d), .from_inp(to_acc), .clk(clk), .inp_in(c_out_acc), .out_o(acc_out), .out_b(0));

    alu alu(.to_acc(to_acc), .bus_d(bus_d), .from_a(a_calc), .from_b(b_calc), .clk(clk), .ad(ad), .sub(sb));



endmodule

Waveform.vcd
$version Generated by VerilatedVcd $end
$timescale 1ps $end

 $scope module TOP $end
  $var wire  8 C bus_i [7:0] $end
  $var wire  1 D clk $end
  $var wire  1 E reset $end
  $scope module top $end
   $var wire  8 @ a_calc [7:0] $end
   $var wire  1 G a_out $end
   $var wire  1 + acc_out $end
   $var wire  1 , ad $end
   $var wire  4 4 address_ir [3:0] $end
   $var wire  8 A b_calc [7:0] $end
   $var wire  1 G b_out $end
   $var wire  8 H bus_d [7:0] $end
   $var wire  8 C bus_i [7:0] $end
   $var wire  8 B c_calc [7:0] $end
   $var wire  1 F c_out_acc $end
   $var wire  1 D clk $end
   $var wire  1 ) in_a $end
   $var wire  1 ' in_b $end
   $var wire  1 % ir_a $end
   $var wire  4 . ir_i [3:0] $end
   $var wire  1 & jmp $end
   $var wire  1 $ mar_a $end
   $var wire  1 * out_a $end
   $var wire  1 ( out_b $end
   $var wire  1 G out_bus $end
   $var wire  1 # pc_a $end
   $var wire  1 E reset $end
   $var wire  1 - sb $end
   $var wire  8 1 to_a [7:0] $end
   $var wire  8 3 to_acc [7:0] $end
   $var wire  8 2 to_b [7:0] $end
   $var wire  8 0 to_ir [7:0] $end
   $var wire  4 / to_ram [3:0] $end
   $scope module accumulator $end
    $var wire  8 B areg [7:0] $end
    $var wire  8 H bus_d [7:0] $end
    $var wire  1 D clk $end
    $var wire  8 3 from_inp [7:0] $end
    $var wire  1 F inp_in $end
    $var wire  1 G out_b $end
    $var wire  1 + out_o $end
    $var wire  8 B to_out [7:0] $end
   $upscope $end
   $scope module alu $end
    $var wire  1 , ad $end
    $var wire  8 H bus_d [7:0] $end
    $var wire  1 D clk $end
    $var wire  8 @ from_a [7:0] $end
    $var wire  8 A from_b [7:0] $end
    $var wire  8 5 out [7:0] $end
    $var wire  1 - sub $end
    $var wire  8 3 to_acc [7:0] $end
   $upscope $end
   $scope module areg $end
    $var wire  8 @ areg [7:0] $end
    $var wire  8 H bus_d [7:0] $end
    $var wire  1 D clk $end
    $var wire  8 1 from_inp [7:0] $end
    $var wire  1 * inp_in $end
    $var wire  1 G out_b $end
    $var wire  1 G out_o $end
    $var wire  8 @ to_out [7:0] $end
   $upscope $end
   $scope module breg $end
    $var wire  8 A areg [7:0] $end
    $var wire  8 H bus_d [7:0] $end
    $var wire  1 D clk $end
    $var wire  8 2 from_inp [7:0] $end
    $var wire  1 ( inp_in $end
    $var wire  1 G out_b $end
    $var wire  1 G out_o $end
    $var wire  8 A to_out [7:0] $end
   $upscope $end
   $scope module control $end
    $var wire  4 K OP_ADD [3:0] $end
    $var wire  4 N OP_DIV [3:0] $end
    $var wire  4 P OP_HLT [3:0] $end
    $var wire  4 O OP_JMP [3:0] $end
    $var wire  4 I OP_LDA [3:0] $end
    $var wire  4 J OP_LDB [3:0] $end
    $var wire  4 M OP_MUL [3:0] $end
    $var wire  4 L OP_SUB [3:0] $end
    $var wire  4 N OP_WRT [3:0] $end
    $var wire  1 + acc_out $end
    $var wire  1 , ad $end
    $var wire  1 G aflag $end
    $var wire  8 H bus_d [7:0] $end
    $var wire  8 C bus_i [7:0] $end
    $var wire  1 D clk $end
    $var wire  1 ) in_a $end
    $var wire  1 ' in_b $end
    $var wire  1 % ir_a $end
    $var wire  4 . ir_i [3:0] $end
    $var wire  1 & jmp $end
    $var wire  1 $ mar_a $end
    $var wire  1 * out_a $end
    $var wire  1 ( out_b $end
    $var wire  1 # pc_a $end
    $var wire  1 E reset $end
    $var wire  1 - sb $end
    $var wire  3 6 stagecount [2:0] $end
   $upscope $end
   $scope module counter $end
    $var wire  8 C bus_i [7:0] $end
    $var wire  1 D clk $end
    $var wire  4 4 from_ir [3:0] $end
    $var wire  1 & jmp $end
    $var wire  4 7 pc [3:0] $end
    $var wire  1 # pc_a $end
    $var wire  1 E reset $end
   $upscope $end
   $scope module ir $end
    $var wire  4 4 address [3:0] $end
    $var wire  8 C bus_i [7:0] $end
    $var wire  1 D clk $end
    $var wire  8 0 from_ram [7:0] $end
    $var wire  4 . instruction [3:0] $end
    $var wire  1 % ir_a $end
    $var wire  1 E reset $end
    $var wire  4 . to_ctrl [3:0] $end
    $var wire  4 4 to_ram [3:0] $end
   $upscope $end
   $scope module mar $end
    $var wire  4 / address [3:0] $end
    $var wire  8 C bus_i [7:0] $end
    $var wire  1 D clk $end
    $var wire  4 4 from_ir [3:0] $end
    $var wire  1 & jmp $end
    $var wire  1 $ mar_a $end
    $var wire  4 Q offset [3:0] $end
    $var wire  1 E reset $end
    $var wire  4 / to_ram [3:0] $end
   $upscope $end
   $scope module ram $end
    $var wire  4 4 address_ir [3:0] $end
    $var wire  1 D clk $end
    $var wire  1 ) in_a $end
    $var wire  1 ' in_b $end
    $var wire  1 + in_c $end
    $var wire  8 = index_ir [7:0] $end
    $var wire  8 > index_reg [7:0] $end
    $var wire  4 / mar_in [3:0] $end
    $var wire 129 8 mem [128:0] $end
    $var wire  1 * out_a $end
    $var wire  1 ( out_b $end
    $var wire  8 0 out_ir [7:0] $end
    $var wire  8 ? out_reg [7:0] $end
    $var wire  1 E reset $end
    $var wire  8 1 to_a [7:0] $end
    $var wire  8 2 to_b [7:0] $end
    $var wire  8 B to_c [7:0] $end
    $var wire  8 0 to_ir [7:0] $end
   $upscope $end
  $upscope $end
 $upscope $end
$enddefinitions $end


#0
0#
0$
0%
0&
0'
0(
0)
0*
0+
0,
0-
b0000 .
b0000 /
b00000000 0
b00000000 1
b00000000 2
b00000000 3
b0000 4
b00000000 5
b000 6
b0000 7
b000000000000000000000000000000000000000000000000000000000000000000000000000000000000000000000000000000000000000000000000000000000 8
b00000000 =
b00000000 >
b00000000 ?
b00000000 @
b00000000 A
b00000000 B
b00000000 C
1D
0E
1F
0G
b00000000 H
b1000 I
b0100 J
b0010 K
b0001 L
b1100 M
b1010 N
b1001 O
b1111 P
b0000 Q
#1
0D
#2
1#
b001 6
b0001 7
b000000000000000000000000000000000111111111000111110100110100001101000011000001100000011101001011100100001010001011000011000000100 8
b00000001 C
1D
#3
0D
#4
0#
1$
b0001 /
b00000100 0
b010 6
b00000100 ?
b00000000 C
1D
#5
0D
#6
0$
1%
b0100 4
b011 6
b00001000 =
b00100000 >
1D
#7
0D
#8
0%
b10000110 0
b100 6
b10010111 ?
1D
#9
0D
#10
b101 6
b00110000 >
1D
#11
0D
#12
b000 6
b00001100 ?
1D
#13
0D
#14
1#
b001 6
b0010 7
b00000010 C
1D
#15
0D
#16
0#
1$
b0010 /
b010 6
b00000000 C
1D
#17
0D
#18
0$
1%
b1000 .
b0110 4
b011 6
b00010000 =
1D
#19
0D
#20
0%
1*
b01000101 0
b00001100 1
b100 6
1D
#21
b00001100 @
0D
#22
0*
b00000000 1
b101 6
b00101000 >
1D
#23
0D
#24
b000 6
b00001110 ?
1D
#25
0D
#26
1#
b001 6
b0011 7
b00000011 C
1D
#27
0D
#28
0#
1$
b0011 /
b010 6
b00000000 C
1D
#29
0D
#30
0$
1%
b0100 .
b0101 4
b011 6
b00011000 =
1D
#31
0D
#32
0%
1(
b00100001 0
b00001110 2
b100 6
1D
#33
b00001110 A
0D
#34
0(
b00000000 2
b101 6
b00001000 >
1D
#35
0D
#36
b000 6
b10000110 ?
1D
#37
0D
#38
1#
b001 6
b0100 7
b00000100 C
1D
#39
0D
#40
0#
1$
b0100 /
b010 6
b00000000 C
1D
#41
0D
#42
0$
1%
b0010 .
b0001 4
b011 6
b00100000 =
1D
#43
0D
#44
0%
1,
b10010111 0
b00011010 5
b100 6
1D
#45
0D
#46
0,
b00011010 3
b101 6
b00111000 >
1D
#47
b00011010 B
0D
#48
b000 6
1D
#49
0D
#50
1#
b001 6
b0101 7
b00000101 C
1D
#51
0D
#52
0#
1$
b0101 /
b010 6
b00000000 C
1D
#53
0D
#54
0$
1%
b1001 .
b0111 4
b011 6
b00101000 =
1D
#55
0D
#56
0%
1&
b0111 /
b00001110 0
b100 6
b0110 7
1D
#57
0D
#58
0&
b101 6
b00111000 =
b01110000 >
1D
#59
0D
#60
b10000110 0
b000 6
b00000000 ?
1D
#61
0D
#62
1#
b001 6
b0111 7
b00110000 >
b00000111 C
1D
#63
0D
#64
0#
1$
b010 6
b00001100 ?
b00000000 C
1D
#65
0D
#66
0$
1%
b1000 .
b0110 4
b011 6
1D
#67
0D
#68
0%
1*
b00001100 1
b100 6
1D
#69
0D
#70
0*
b00000000 1
b101 6
1D
#71
0D
#72
b000 6
1D
#73
0D
#74
1#
b001 6
b1000 7
b00001000 C
1D
#75
0D
#76
0#
1$
b1000 /
b010 6
b00000000 C
1D
#77
0D
#78
0$
1%
b011 6
b01000000 =
1D
#79
0D
#80
0%
1*
b00001100 1
b100 6
1D
#81
0D
#82
0*
b00000000 1
b101 6
1D
#83
0D
#84
b000 6
1D
#85
0D
#86
1#
b001 6
b1001 7
b00001001 C
1D
#87
0D
#88
0#
1$
b1001 /
b010 6
b00000000 C
1D
#89
0D
#90
0$
1%
b011 6
b01001000 =
1D
#91
0D
#92
0%
1*
b10100110 0
b00001100 1
b100 6
1D
#93
0D
#94
0*
b00000000 1
b101 6
1D
#95
0D
#96
b000 6
1D
#97
0D
#98
1#
b001 6
b1010 7
b00001010 C
1D
#99
0D
#100
0#
1$
b1010 /
b010 6
b00000000 C
1D
#101
0D
#102
0$
1%
b1010 .
b011 6
b01010000 =
1D
#103
0D
#104
0%
1+
b10001111 0
b100 6
b000011010000000000000000000000000111111111000111110100110100001101000011000001100000011101001011100100001010001011000011000000100 8
1D
#105
0D
#106
0+
b101 6
b01111000 >
1D
#107
0D
#108
b000 6
b00011010 ?
1D
#109
0D
#110
1#
b001 6
b1011 7
b00001011 C
1D
#111
0D
#112
0#
1$
b1011 /
b010 6
b00000000 C
1D
#113
0D
#114
0$
1%
b1000 .
b1111 4
b011 6
b01011000 =
1D
#115
0D
#116
0%
1*
b11111111 0
b00011010 1
b100 6
1D
#117
b00011010 @
0D
#118
0*
b00000000 1
b101 6
1D
#119
0D
#120
b000 6
1D
#121
0D
#122
1#
b001 6
b1100 7
b00001100 C
1D
#123
0D
#124
0#
1$
b1100 /
b010 6
b00000000 C
1D
#125
0D
#126
0$
1%
b1111 .
b011 6
b01100000 =
1D
#127
0D
#128
0%
b00000000 0
1D
#129
0D
#130
b00000000 >
1D
#131
0D
#132
b00000100 ?
1D
