cpuf.v
// LITTLE ENDIAN
// First four bytes are instruction, last four address
// verilator lint_off BLKANDNBLK

// INSTRUCTIONS
// [_ _ _ _][_ _ _ _]
//   Instr.   Addr.
// OP_LDA : 1000 => Load value at address into register A
// OP_LDB : 0100 => Load value at address into register B
// OP_ADD : 0010 => Add values in Register A and B and dump in accumulator
// OP_SUB : 0001 => Subtract value in B from register A and dump in accumulator
// OP_JMP : 1001 => Jump to instruction at address
// OP_HLT : 1111 => Halt 
// OP_WRT : 1010 => Write accumulator contents to RAM
// OP_DMA : 1101 => Dump A register into data bus
// OP_DMB : 1011 => Dump B register into data bus

// STUFF ON Instruction Bus
module program_counter(inout [7:0] bus_i, input clk, input reset, input pc_a, input [3:0] from_ir, input jmp);
    
    reg [3:0] pc;
    
    always @(posedge clk) begin
        if (reset)
            pc <= 0;
        else if (pc_a)
            pc <= pc + 1; 
        else if (jmp)
            pc <= from_ir - 4'b0001;
    end

    assign bus_i = (pc_a) ? {4'bz,pc} : 8'bz;

endmodule

module instruction_register(inout [7:0] bus_i, input [7:0] from_ram, output [3:0] to_ctrl, output [3:0] to_ram, input clk, input reset, input ir_a);

    reg [3:0] instruction;
    reg [3:0] address; // Address in instruction

    always @(posedge clk) begin
        if (reset) begin
            instruction <= 0;
        end
        else if (ir_a) begin
            address <= from_ram[3:0];
            instruction <= from_ram[7:4];
        end 
    end

    //assign bus_i = (out_b) ? {instruction,4'bz} : 8'bz;
    assign to_ctrl = (1) ? instruction : 4'bz;
    assign to_ram = address;

endmodule

module mar(inout [7:0] bus_i, output [3:0] to_ram, input [3:0] from_ir, input clk, input reset, input mar_a, input jmp);

    reg [3:0] address;
    reg [3:0] offset;

    always @(posedge clk) begin
        if (mar_a) begin
            address <= bus_i[3:0];
        end
        else if (jmp) begin
            address <= from_ir;
            
        end
        //else
        //    address <= from_ir;
    end

    //assign to_ram = (mar_a) ? address : 4'bz;
    assign to_ram = address;
endmodule
// -----

// RAM
module ram(output [7:0] to_ir, inout [7:0] to_a, inout [7:0] to_b, inout [7:0] to_c, input [3:0] mar_in, input [3:0] address_ir, input in_c, input in_b, input out_b, input in_a, input out_a, input clk, input reset);

    reg [128:0] mem;
    reg [7:0] index_ir;
    reg [7:0] index_reg;
    reg [7:0] out_reg;
    reg [7:0] out_ir;

    always @(posedge clk) begin
        // Contents of RAM, including data and the program itself
        mem[7:0] <= 8'b00000100;
        mem[15:8] <= 8'b10000110; //LDA 0110
        mem[23:16] <= 8'b01000101; //LDB 0111
        mem[31:24] <= 8'b00100001; //ADD
        mem[39:32] <= 8'b10010111; //JMP 0111
        mem[47:40] <= 8'b00001110;
        mem[55:48] <= 8'b00001100;
        mem[63:56] <= 8'b10000110; //LDA 0101
        mem[71:64] <= 8'b10000110; //LDA 0110
        mem[79:72] <= 8'b10100110; //WRT
        mem[87:80] <= 8'b10001111; //LDA 1000
        mem[95:88] <= 8'b10111111; //DMA
        mem[103:96] <= 8'b11111111; //HLT
        
        if(reset) begin
            //index <= 0;
            //out <= 0;
        end
        else if(in_c) begin
            mem[127:120] <= to_c;
        end
        else if(in_a) begin
            mem[119:112] <= to_a;
        end


        index_ir <= mar_in * 8;
        out_ir <= mem[index_ir +: 8];

        index_reg <= out_ir[3:0] * 8;
        out_reg <= mem[index_reg +: 8];

    end

    assign to_a = (out_a) ? out_reg : 8'bz;
    assign to_b = (out_b) ? out_reg : 8'bz;
    assign to_ir = out_ir;

endmodule
// Stuff on data bus

module register(output [7:0] to_out, inout [7:0] bus_d, input [7:0] from_inp, input clk, input inp_in, input out_o, input out_b);

    reg [7:0] areg;

    always @(negedge clk) begin
        if (inp_in)
            areg <= from_inp;
    end

    assign bus_d = (out_b) ? areg : 8'bz;
    assign to_out = areg;


endmodule

module alu(output reg [7:0] to_acc, inout [7:0] bus_d, input [7:0] from_a, input [7:0] from_b, input clk, input ad, input sub);
    reg [7:0] out;
    
    always @(posedge clk) begin
        if(ad)
            out <= from_a + from_b;
        if(sub)
            out <= from_a - from_b;
    
    assign to_acc = (1) ? out : 8'bz; //ad || sub

    end

endmodule

module controller(inout [7:0] bus_i, inout [7:0] bus_d, output reg pc_a, output reg mar_a, output reg ir_a, output reg in_a, output reg out_a, output reg in_b, output reg out_b, output reg ad, output reg sb, output reg jmp, output reg acc_out, output reg a_out_bus, output reg b_out_bus, input [3:0] ir_i, input clk, input reset);
    reg [2:0] stagecount = 0;
    reg aflag = 0;

    // CODES

    parameter OP_LDA = 4'b1000;
    parameter OP_LDB = 4'b0100;
    parameter OP_ADD = 4'b0010;
    parameter OP_SUB = 4'b0001;
    parameter OP_JMP = 4'b1001;
    parameter OP_HLT = 4'b1111;
    parameter OP_WRT = 4'b1010;
    parameter OP_DMA = 4'b1011;
    parameter OP_DMB = 4'b1101;


    // Control word: pc_a, mar_a, ir_a, in_a (input to ram), out_a (output from ram), in_b, out_b, ad, sb, jmp, acc_out, a_out_bus, b_out_bus

    always @(posedge clk) begin
        if (ir_i == OP_HLT) begin
            pc_a = 0;
            mar_a = 0;
            ir_a = 0;
            in_a = 0;
            out_a = 0;
            in_b = 0;
            out_b = 0;
            ad = 0;
            sb = 0;
            jmp = 0;
            acc_out = 0;
        end
        else begin
            stagecount = stagecount + 1;
            if (stagecount == 6) begin
                pc_a = 0;
                mar_a = 0;
                ir_a = 0;
                in_a = 0;
                out_a = 0;
                in_b = 0;
                out_b = 0;
                ad = 0;
                sb = 0;
                jmp = 0;
                acc_out = 0;
                //a_out_bus = 0;
                //b_out_bus = 0;
                //ctrl_wd = 000;
                stagecount = 0;
            end
            // First 3 stages are always the same
            if (stagecount == 1) begin
                pc_a = 1;
                mar_a = 0; //0
                ir_a = 0; //0
                in_a = 0;
                out_a = 0;
                in_b = 0;
                out_b = 0;
                ad = 0;
                sb = 0;
                jmp = 0;
                acc_out = 0;
                //a_out_bus = 0;
                //b_out_bus = 0;
                //ctrl_wd = 110;
            end
            if (stagecount == 2) begin
                pc_a = 0;
                mar_a = 1;
                ir_a = 0; //0
                in_a = 0;
                out_a = 0;
                in_b = 0;
                out_b = 0;
                jmp = 0;
                acc_out = 0;
                //a_out_bus = 0;
                //b_out_bus = 0;
                //ctrl_wd = 010;
            end
            if (stagecount == 3) begin
                pc_a = 0;
                mar_a = 0;
                ir_a = 1; //1
                in_a = 0;
                out_a = 0;
                in_b = 0;
                out_b = 0;
                ad = 0;
                sb = 0;
                jmp = 0;
                acc_out = 0;
                //a_out_bus = 0;
                //b_out_bus = 0;
                //ctrl_wd = 001;
            end
            if (ir_i == OP_JMP) begin
                if (stagecount == 4) begin
                    pc_a = 0;
                    mar_a = 0;
                    ir_a = 0;
                    in_a = 0;
                    out_a = 0;
                    in_b = 0;
                    out_b = 0;
                    ad = 0;
                    sb = 0;
                    jmp = 1;
                    acc_out = 0;
                    a_out_bus = 0;
                    b_out_bus = 0;
                end
                if (stagecount == 5) begin
                    pc_a = 0;
                    mar_a = 0;
                    ir_a = 0;
                    in_a = 0;
                    out_a = 0;
                    in_b = 0;
                    out_b = 0;
                    ad = 0;
                    sb = 0;
                    jmp = 0;
                    acc_out = 0;
                    a_out_bus = 0;
                    b_out_bus = 0;
                end

            end
            else begin
                if (ir_i == OP_LDA) begin
                    if (stagecount == 4) begin
                        pc_a = 0;
                        mar_a = 0;
                        ir_a = 0;
                        in_a = 0;
                        out_a = 1;
                        in_b = 0;
                        out_b = 0;
                        ad = 0;
                        sb = 0;
                        jmp = 0;
                        acc_out = 0;
                        a_out_bus = 0;
                        b_out_bus = 0;
                    end
                    if (stagecount == 5) begin
                        pc_a = 0;
                        mar_a = 0;
                        ir_a = 0;
                        in_a = 0;
                        out_a = 0;
                        in_b = 0;
                        out_b = 0;
                        ad = 0;
                        sb = 0;
                        jmp = 0;
                        acc_out = 0;
                        a_out_bus = 0;
                        b_out_bus = 0;
                    end
                end 
                else if (ir_i == OP_LDB) begin
                    if (stagecount == 4) begin
                        pc_a = 0;
                        mar_a = 0;
                        ir_a = 0;
                        in_a = 0;
                        out_a = 0;
                        in_b = 0;
                        out_b = 1;
                        ad = 0;
                        sb = 0;
                        jmp = 0;
                        acc_out = 0;
                        a_out_bus = 0;
                        b_out_bus = 0;
                    end
                    if (stagecount == 5) begin
                        pc_a = 0;
                        mar_a = 0;
                        ir_a = 0;
                        in_a = 0;
                        out_a = 0;
                        in_b = 0;
                        out_b = 0;
                        ad = 0;
                        sb = 0;
                        jmp = 0;
                        acc_out = 0;
                        a_out_bus = 0;
                        b_out_bus = 0;
                    end
                end
                else if (ir_i == OP_ADD) begin
                    if (stagecount == 4) begin
                        pc_a = 0;
                        mar_a = 0;
                        ir_a = 0;
                        in_a = 0;
                        out_a = 0;
                        in_b = 0;
                        out_b = 0;
                        ad = 1;
                        sb = 0;
                        jmp = 0;
                        acc_out = 0;
                        a_out_bus = 0;
                        b_out_bus = 0;
                    end
                    if (stagecount == 5) begin
                        pc_a = 0;
                        mar_a = 0;
                        ir_a = 0;
                        in_a = 0;
                        out_a = 0;
                        in_b = 0;
                        out_b = 0;
                        ad = 0;
                        sb = 0;
                        jmp = 0;
                        acc_out = 0;
                        a_out_bus = 0;
                        b_out_bus = 0;
                    end
                end
                else if (ir_i == OP_SUB) begin
                    if (stagecount == 4) begin
                        pc_a = 0;
                        mar_a = 0;
                        ir_a = 0;
                        in_a = 0;
                        out_a = 0;
                        in_b = 0;
                        out_b = 0;
                        ad = 0;
                        sb = 1;
                        jmp = 0;
                        acc_out = 0;
                        a_out_bus = 0;
                        b_out_bus = 0;
                    end
                    if (stagecount == 5) begin
                        pc_a = 0;
                        mar_a = 0;
                        ir_a = 0;
                        in_a = 0;
                        out_a = 0;
                        in_b = 0;
                        out_b = 0;
                        ad = 0;
                        sb = 0;
                        jmp = 0;
                        acc_out = 0;
                        a_out_bus = 0;
                        b_out_bus = 0;
                    end
                end
                else if (ir_i == OP_WRT) begin
                    if (stagecount == 4) begin
                        pc_a = 0;
                        mar_a = 0;
                        ir_a = 0;
                        in_a = 0;
                        out_a = 0;
                        in_b = 0;
                        out_b = 0;
                        ad = 0;
                        sb = 0;
                        jmp = 0;
                        acc_out = 1;
                        a_out_bus = 0;
                        b_out_bus = 0;
                    end
                    if (stagecount == 5) begin
                        pc_a = 0;
                        mar_a = 0;
                        ir_a = 0;
                        in_a = 0;
                        out_a = 0;
                        in_b = 0;
                        out_b = 0;
                        ad = 0;
                        sb = 0;
                        jmp = 0;
                        acc_out = 0;
                        a_out_bus = 0;
                        b_out_bus = 0;
                    end
                end
                else if (ir_i == OP_DMA) begin
                    if (stagecount == 4) begin
                        pc_a = 0;
                        mar_a = 0;
                        ir_a = 0;
                        in_a = 0;
                        out_a = 0;
                        in_b = 0;
                        out_b = 0;
                        ad = 0;
                        sb = 0;
                        jmp = 0;
                        acc_out = 0;
                        a_out_bus = 1;
                        b_out_bus = 0;
                    end
                    if (stagecount == 5) begin
                        pc_a = 0;
                        mar_a = 0;
                        ir_a = 0;
                        in_a = 0;
                        out_a = 0;
                        in_b = 0;
                        out_b = 0;
                        ad = 0;
                        sb = 0;
                        jmp = 0;
                        acc_out = 0;
                        a_out_bus = 1;
                        b_out_bus = 0;
                    end
                end
                else if (ir_i == OP_DMB) begin
                    if (stagecount == 4) begin
                        pc_a = 0;
                        mar_a = 0;
                        ir_a = 0;
                        in_a = 0;
                        out_a = 0;
                        in_b = 0;
                        out_b = 0;
                        ad = 0;
                        sb = 0;
                        jmp = 0;
                        acc_out = 0;
                        a_out_bus = 0;
                        b_out_bus = 1;
                    end
                    if (stagecount == 5) begin
                        pc_a = 0;
                        mar_a = 0;
                        ir_a = 0;
                        in_a = 0;
                        out_a = 0;
                        in_b = 0;
                        out_b = 0;
                        ad = 0;
                        sb = 0;
                        jmp = 0;
                        acc_out = 0;
                        a_out_bus = 0;
                        b_out_bus = 1;
                    end
                end
                else begin
                    if (stagecount == 4) begin
                        pc_a = 0;
                        mar_a = 0;
                        ir_a = 0;
                        in_a = 0;
                        out_a = 0;
                        in_b = 0;
                        out_b = 0;
                        ad = 0;
                        sb = 0;
                        jmp = 0;
                        acc_out = 0;
                        a_out_bus = 0;
                        b_out_bus = 0;
                    end
                    if (stagecount == 5) begin
                        pc_a = 0;
                        mar_a = 0;
                        ir_a = 0;
                        in_a = 0;
                        out_a = 0;
                        in_b = 0;
                        out_b = 0;
                        ad = 0;
                        sb = 0;
                        jmp = 0;
                        acc_out = 0;
                        a_out_bus = 0;
                        b_out_bus = 0;
                    end
                end
            end
        end
    end
endmodule

module cpu(output [7:0] bus_i, output [7:0] bus_d, input clk, input reset);
    reg pc_a = 0;
    reg mar_a = 0;
    reg ir_a = 0;
    reg jmp = 0;
    // RAM flags
    reg in_b = 0;
    reg out_b = 0;
    reg in_a = 0;
    reg out_a = 0;
    //-----
    // accumulator
    reg c_out_acc = 1; //calculator out
    reg acc_out = 0;
    reg ad = 0;
    reg sb = 0;
    // Register flags (BUS OUT)
    reg a_out = 0;
    reg b_out = 0;
    //----
    reg out_bus = 0;
    reg [3:0] ir_i;
    //reg [7:0] bus_d;
    //reg [7:0] bus_i;
    wire [3:0] to_ram;
    wire [7:0] to_ir;
    wire [7:0] to_a;
    wire [7:0] to_b;
    wire [7:0] to_acc;
    wire [7:0] a_calc;
    wire [7:0] b_calc;
    wire [7:0] c_calc;
    wire [3:0] address_ir;

    controller control(.bus_i(bus_i), .bus_d(bus_d), .pc_a(pc_a), .mar_a(mar_a), .ir_a(ir_a), .in_a(in_a), .out_a(out_a), .in_b(in_b), .out_b(out_b), .ad(ad), .sb(sb), .jmp(jmp), .acc_out(acc_out), .a_out_bus(a_out), .b_out_bus(b_out), .ir_i(ir_i), .clk(clk), .reset(reset));

    program_counter counter(.bus_i(bus_i), .clk(clk), .reset(reset), .pc_a(pc_a), .from_ir(address_ir), .jmp(jmp));

    mar mar(.bus_i(bus_i), .to_ram(to_ram), .from_ir(address_ir), .clk(clk), .reset(reset), .mar_a(mar_a), .jmp(jmp));

    ram ram(.to_ir(to_ir), .to_a(to_a), .to_b(to_b), .to_c(c_calc), .mar_in(to_ram), .address_ir(address_ir), .in_c(acc_out), .in_b(in_b), .out_b(out_b), .in_a(in_a), .out_a(out_a), .clk(clk), .reset(reset));

    instruction_register ir(.bus_i(bus_i), .from_ram(to_ir), .to_ctrl(ir_i), .to_ram(address_ir), .clk(clk), .reset(reset), .ir_a(ir_a));

    register areg(.to_out(a_calc), .bus_d(bus_d), .from_inp(to_a), .clk(clk), .inp_in(out_a), .out_o(0), .out_b(a_out));
    
    //register breg(.to_c(b_calc), .bus_d(bus_d), .from_ram(to_b), .clk(clk), .ram_in(out_b), .out_b(b_out));
    register breg(.to_out(b_calc), .bus_d(bus_d), .from_inp(to_b), .clk(clk), .inp_in(out_b), .out_o(0), .out_b(b_out));

    register accumulator(.to_out(c_calc), .bus_d(bus_d), .from_inp(to_acc), .clk(clk), .inp_in(c_out_acc), .out_o(acc_out), .out_b(0));

    alu alu(.to_acc(to_acc), .bus_d(bus_d), .from_a(a_calc), .from_b(b_calc), .clk(clk), .ad(ad), .sub(sb));

endmodule

module top(output [7:0] led_1, output [7:0] led_2, input clk, input reset);

    cpu cpu(.bus_i(led_2), .bus_d(led_1), .clk(clk), .reset(reset));

endmodule

Waveform.vcd
$version Generated by VerilatedVcd $end
$timescale 1ps $end

 $scope module TOP $end
  $var wire  1 G clk $end
  $var wire  8 E led_1 [7:0] $end
  $var wire  8 F led_2 [7:0] $end
  $var wire  1 H reset $end
  $scope module top $end
   $var wire  1 G clk $end
   $var wire  8 E led_1 [7:0] $end
   $var wire  8 F led_2 [7:0] $end
   $var wire  1 H reset $end
   $scope module cpu $end
    $var wire  8 B a_calc [7:0] $end
    $var wire  1 . a_out $end
    $var wire  1 + acc_out $end
    $var wire  1 , ad $end
    $var wire  4 6 address_ir [3:0] $end
    $var wire  8 C b_calc [7:0] $end
    $var wire  1 / b_out $end
    $var wire  8 E bus_d [7:0] $end
    $var wire  8 F bus_i [7:0] $end
    $var wire  8 D c_calc [7:0] $end
    $var wire  1 I c_out_acc $end
    $var wire  1 G clk $end
    $var wire  1 ) in_a $end
    $var wire  1 ' in_b $end
    $var wire  1 % ir_a $end
    $var wire  4 0 ir_i [3:0] $end
    $var wire  1 & jmp $end
    $var wire  1 $ mar_a $end
    $var wire  1 * out_a $end
    $var wire  1 ( out_b $end
    $var wire  1 J out_bus $end
    $var wire  1 # pc_a $end
    $var wire  1 H reset $end
    $var wire  1 - sb $end
    $var wire  8 3 to_a [7:0] $end
    $var wire  8 5 to_acc [7:0] $end
    $var wire  8 4 to_b [7:0] $end
    $var wire  8 2 to_ir [7:0] $end
    $var wire  4 1 to_ram [3:0] $end
    $scope module accumulator $end
     $var wire  8 D areg [7:0] $end
     $var wire  8 E bus_d [7:0] $end
     $var wire  1 G clk $end
     $var wire  8 5 from_inp [7:0] $end
     $var wire  1 I inp_in $end
     $var wire  1 J out_b $end
     $var wire  1 + out_o $end
     $var wire  8 D to_out [7:0] $end
    $upscope $end
    $scope module alu $end
     $var wire  1 , ad $end
     $var wire  8 E bus_d [7:0] $end
     $var wire  1 G clk $end
     $var wire  8 B from_a [7:0] $end
     $var wire  8 C from_b [7:0] $end
     $var wire  8 7 out [7:0] $end
     $var wire  1 - sub $end
     $var wire  8 5 to_acc [7:0] $end
    $upscope $end
    $scope module areg $end
     $var wire  8 B areg [7:0] $end
     $var wire  8 E bus_d [7:0] $end
     $var wire  1 G clk $end
     $var wire  8 3 from_inp [7:0] $end
     $var wire  1 * inp_in $end
     $var wire  1 . out_b $end
     $var wire  1 J out_o $end
     $var wire  8 B to_out [7:0] $end
    $upscope $end
    $scope module breg $end
     $var wire  8 C areg [7:0] $end
     $var wire  8 E bus_d [7:0] $end
     $var wire  1 G clk $end
     $var wire  8 4 from_inp [7:0] $end
     $var wire  1 ( inp_in $end
     $var wire  1 / out_b $end
     $var wire  1 J out_o $end
     $var wire  8 C to_out [7:0] $end
    $upscope $end
    $scope module control $end
     $var wire  4 M OP_ADD [3:0] $end
     $var wire  4 R OP_DMA [3:0] $end
     $var wire  4 S OP_DMB [3:0] $end
     $var wire  4 P OP_HLT [3:0] $end
     $var wire  4 O OP_JMP [3:0] $end
     $var wire  4 K OP_LDA [3:0] $end
     $var wire  4 L OP_LDB [3:0] $end
     $var wire  4 N OP_SUB [3:0] $end
     $var wire  4 Q OP_WRT [3:0] $end
     $var wire  1 . a_out_bus $end
     $var wire  1 + acc_out $end
     $var wire  1 , ad $end
     $var wire  1 J aflag $end
     $var wire  1 / b_out_bus $end
     $var wire  8 E bus_d [7:0] $end
     $var wire  8 F bus_i [7:0] $end
     $var wire  1 G clk $end
     $var wire  1 ) in_a $end
     $var wire  1 ' in_b $end
     $var wire  1 % ir_a $end
     $var wire  4 0 ir_i [3:0] $end
     $var wire  1 & jmp $end
     $var wire  1 $ mar_a $end
     $var wire  1 * out_a $end
     $var wire  1 ( out_b $end
     $var wire  1 # pc_a $end
     $var wire  1 H reset $end
     $var wire  1 - sb $end
     $var wire  3 8 stagecount [2:0] $end
    $upscope $end
    $scope module counter $end
     $var wire  8 F bus_i [7:0] $end
     $var wire  1 G clk $end
     $var wire  4 6 from_ir [3:0] $end
     $var wire  1 & jmp $end
     $var wire  4 9 pc [3:0] $end
     $var wire  1 # pc_a $end
     $var wire  1 H reset $end
    $upscope $end
    $scope module ir $end
     $var wire  4 6 address [3:0] $end
     $var wire  8 F bus_i [7:0] $end
     $var wire  1 G clk $end
     $var wire  8 2 from_ram [7:0] $end
     $var wire  4 0 instruction [3:0] $end
     $var wire  1 % ir_a $end
     $var wire  1 H reset $end
     $var wire  4 0 to_ctrl [3:0] $end
     $var wire  4 6 to_ram [3:0] $end
    $upscope $end
    $scope module mar $end
     $var wire  4 1 address [3:0] $end
     $var wire  8 F bus_i [7:0] $end
     $var wire  1 G clk $end
     $var wire  4 6 from_ir [3:0] $end
     $var wire  1 & jmp $end
     $var wire  1 $ mar_a $end
     $var wire  4 T offset [3:0] $end
     $var wire  1 H reset $end
     $var wire  4 1 to_ram [3:0] $end
    $upscope $end
    $scope module ram $end
     $var wire  4 6 address_ir [3:0] $end
     $var wire  1 G clk $end
     $var wire  1 ) in_a $end
     $var wire  1 ' in_b $end
     $var wire  1 + in_c $end
     $var wire  8 ? index_ir [7:0] $end
     $var wire  8 @ index_reg [7:0] $end
     $var wire  4 1 mar_in [3:0] $end
     $var wire 129 : mem [128:0] $end
     $var wire  1 * out_a $end
     $var wire  1 ( out_b $end
     $var wire  8 2 out_ir [7:0] $end
     $var wire  8 A out_reg [7:0] $end
     $var wire  1 H reset $end
     $var wire  8 3 to_a [7:0] $end
     $var wire  8 4 to_b [7:0] $end
     $var wire  8 D to_c [7:0] $end
     $var wire  8 2 to_ir [7:0] $end
    $upscope $end
   $upscope $end
  $upscope $end
 $upscope $end
$enddefinitions $end


#0
0#
0$
0%
0&
0'
0(
0)
0*
0+
0,
0-
0.
0/
b0000 0
b0000 1
b00000000 2
b00000000 3
b00000000 4
b00000000 5
b0000 6
b00000000 7
b000 8
b0000 9
b000000000000000000000000000000000000000000000000000000000000000000000000000000000000000000000000000000000000000000000000000000000 :
b00000000 ?
b00000000 @
b00000000 A
b00000000 B
b00000000 C
b00000000 D
b00000000 E
b00000000 F
1G
0H
1I
0J
b1000 K
b0100 L
b0010 M
b0001 N
b1001 O
b1111 P
b1010 Q
b1011 R
b1101 S
b0000 T
#1
0G
#2
1#
b001 8
b0001 9
b000000000000000000000000011111111101111111000111110100110100001101000011000001100000011101001011100100001010001011000011000000100 :
b00000001 F
1G
#3
0G
#4
0#
1$
b0001 1
b00000100 2
b010 8
b00000100 A
b00000000 F
1G
#5
0G
#6
0$
1%
b0100 6
b011 8
b00001000 ?
b00100000 @
1G
#7
0G
#8
0%
b10000110 2
b100 8
b10010111 A
1G
#9
0G
#10
b101 8
b00110000 @
1G
#11
0G
#12
b000 8
b00001100 A
1G
#13
0G
#14
1#
b001 8
b0010 9
b00000010 F
1G
#15
0G
#16
0#
1$
b0010 1
b010 8
b00000000 F
1G
#17
0G
#18
0$
1%
b1000 0
b0110 6
b011 8
b00010000 ?
1G
#19
0G
#20
0%
1*
b01000101 2
b00001100 3
b100 8
1G
#21
b00001100 B
0G
#22
0*
b00000000 3
b101 8
b00101000 @
1G
#23
0G
#24
b000 8
b00001110 A
1G
#25
0G
#26
1#
b001 8
b0011 9
b00000011 F
1G
#27
0G
#28
0#
1$
b0011 1
b010 8
b00000000 F
1G
#29
0G
#30
0$
1%
b0100 0
b0101 6
b011 8
b00011000 ?
1G
#31
0G
#32
0%
1(
b00100001 2
b00001110 4
b100 8
1G
#33
b00001110 C
0G
#34
0(
b00000000 4
b101 8
b00001000 @
1G
#35
0G
#36
b000 8
b10000110 A
1G
#37
0G
#38
1#
b001 8
b0100 9
b00000100 F
1G
#39
0G
#40
0#
1$
b0100 1
b010 8
b00000000 F
1G
#41
0G
#42
0$
1%
b0010 0
b0001 6
b011 8
b00100000 ?
1G
#43
0G
#44
0%
1,
b10010111 2
b00011010 7
b100 8
1G
#45
0G
#46
0,
b00011010 5
b101 8
b00111000 @
1G
#47
b00011010 D
0G
#48
b000 8
1G
#49
0G
#50
1#
b001 8
b0101 9
b00000101 F
1G
#51
0G
#52
0#
1$
b0101 1
b010 8
b00000000 F
1G
#53
0G
#54
0$
1%
b1001 0
b0111 6
b011 8
b00101000 ?
1G
#55
0G
#56
0%
1&
b0111 1
b00001110 2
b100 8
b0110 9
1G
#57
0G
#58
0&
b101 8
b00111000 ?
b01110000 @
1G
#59
0G
#60
b10000110 2
b000 8
b00000000 A
1G
#61
0G
#62
1#
b001 8
b0111 9
b00110000 @
b00000111 F
1G
#63
0G
#64
0#
1$
b010 8
b00001100 A
b00000000 F
1G
#65
0G
#66
0$
1%
b1000 0
b0110 6
b011 8
1G
#67
0G
#68
0%
1*
b00001100 3
b100 8
1G
#69
0G
#70
0*
b00000000 3
b101 8
1G
#71
0G
#72
b000 8
1G
#73
0G
#74
1#
b001 8
b1000 9
b00001000 F
1G
#75
0G
#76
0#
1$
b1000 1
b010 8
b00000000 F
1G
#77
0G
#78
0$
1%
b011 8
b01000000 ?
1G
#79
0G
#80
0%
1*
b00001100 3
b100 8
1G
#81
0G
#82
0*
b00000000 3
b101 8
1G
#83
0G
#84
b000 8
1G
#85
0G
#86
1#
b001 8
b1001 9
b00001001 F
1G
#87
0G
#88
0#
1$
b1001 1
b010 8
b00000000 F
1G
#89
0G
#90
0$
1%
b011 8
b01001000 ?
1G
#91
0G
#92
0%
1*
b10100110 2
b00001100 3
b100 8
1G
#93
0G
#94
0*
b00000000 3
b101 8
1G
#95
0G
#96
b000 8
1G
#97
0G
#98
1#
b001 8
b1010 9
b00001010 F
1G
#99
0G
#100
0#
1$
b1010 1
b010 8
b00000000 F
1G
#101
0G
#102
0$
1%
b1010 0
b011 8
b01010000 ?
1G
#103
0G
#104
0%
1+
b10001111 2
b100 8
b000011010000000000000000011111111101111111000111110100110100001101000011000001100000011101001011100100001010001011000011000000100 :
1G
#105
0G
#106
0+
b101 8
b01111000 @
1G
#107
0G
#108
b000 8
b00011010 A
1G
#109
0G
#110
1#
b001 8
b1011 9
b00001011 F
1G
#111
0G
#112
0#
1$
b1011 1
b010 8
b00000000 F
1G
#113
0G
#114
0$
1%
b1000 0
b1111 6
b011 8
b01011000 ?
1G
#115
0G
#116
0%
1*
b10111111 2
b00011010 3
b100 8
1G
#117
b00011010 B
0G
#118
0*
b00000000 3
b101 8
1G
#119
0G
#120
b000 8
1G
#121
0G
#122
1#
b001 8
b1100 9
b00001100 F
1G
#123
0G
#124
0#
1$
b1100 1
b010 8
b00000000 F
1G
#125
0G
#126
0$
1%
b1011 0
b011 8
b01100000 ?
1G
#127
0G
#128
0%
1.
b11111111 2
b100 8
b00011010 E
1G
#129
0G
#130
b101 8
1G
#131
0G
#132
b000 8
1G
#133
0G
#134
1#
b001 8
b1101 9
b00001101 F
1G
#135
0G
#136
0#
1$
b1101 1
b010 8
b00000000 F
1G
#137
0G
#138
0$
1%
b1111 0
b011 8
b01101000 ?
1G
#139
0G
#140
0%
b00000000 2
1G
#141
0G
#142
b00000000 @
1G
#143
0G
#144
b00000100 A
1G
