cpuf.v
// LITTLE ENDIAN
// First four bytes are instruction, last four address
// verilator lint_off BLKANDNBLK

// INSTRUCTIONS
// [_ _ _ _][_ _ _ _]
//   Instr.   Addr.
// OP_LDA : 1000 => Load value at address into register A
// OP_LDB : 0100 => Load value at address into register B
// OP_ADD : 0010 => Add values in Register A and bus and dump in register B
// OP_SUB : 0001 => Subtract value in  bus from register A
// OP_MUL : 1100 => Mutiply A and value in bus and dump in register B
// OP_DIV : 1010 => Divide A by value in bus and dump in register B
// OP_JMP : 1001 => Jump to instruction at address
// OP_HLT : 1111 => Halt 

// STUFF ON Instruction Bus
module program_counter(inout [7:0] bus_i, input clk, input reset, input pc_a);
    
    reg [3:0] pc;
    
    always @(posedge clk) begin
        if (reset)
            pc <= 0;
        else if (pc_a)
            pc <= pc + 1; 
    end

    assign bus_i = (pc_a) ? {4'bz,pc} : 8'bz;

endmodule

module instruction_register(inout [7:0] bus_i, input [7:0] from_ram, output [3:0] to_ctrl, input clk, input reset, input ir_a);

    reg [3:0] instruction;

    always @(posedge clk) begin
        if (reset)
            instruction <= 0;
        else if (ir_a)
            instruction <= from_ram[7:4]; 
    end

    //assign bus_i = (out_b) ? {instruction,4'bz} : 8'bz;
    assign to_ctrl = (ir_a) ? instruction : 4'bz;

endmodule

module mar(inout [7:0] bus_i, output [3:0] to_ram, input clk, input reset, input mar_a);

    reg [3:0] address;

    always @(posedge clk) begin
        if(reset)
            address <= 0;
        else if (mar_a)
            address <= bus_i[3:0];
    end

    assign to_ram = (mar_a) ? address : 4'bz;

endmodule
// -----

// RAM
module ram(output [7:0] to_ir, inout [7:0] to_a, inout [7:0] to_b, input [3:0] mar_in, input in_b, input out_b, input in_a, input out_a, input clk, input reset);

    reg [128:0] mem;
    reg [7:0] index;
    reg [7:0] out;

    always @(posedge clk) begin
        mem[7:0] <= 8'b00000000;
        mem[15:8] <= 8'b01000001;
        mem[23:16] <= 8'b11111111;
        mem[31:24] <= 8'b00000010;
        mem[39:32] <= 8'b00000001;
        mem[47:40] <= 8'b10001001;
        if(reset) begin
            index <= 0;
            out <= 0;
        end
        else if(in_b) begin
            mem[127:120] <= to_b;
        end
        else if(in_a) begin
            mem[119:112] <= to_a;
        end
        index <= mar_in * 8;
        out <= mem[index +: 8];
    end

    assign to_a = (out_a) ? out : 8'bz;
    assign to_b = (out_b) ? out : 8'bz;
    assign to_ir = out;

endmodule
// Stuff on data bus

module register(inout [7:0] bus_d, input [7:0] from_ram, input clk, input ram_in, input out_b);

    reg [7:0] areg;

    always @(posedge clk) begin
        if (ram_in)
            areg <= from_ram;
    end

    assign bus_d = (out_b) ? areg : 8'bz;


endmodule


module alu(inout [7:0] bus_d, input [7:0] from_a, output [7:0] to_b, input ad, input sub);
    reg [7:0] out;
    
    always @(posedge clk) begin
        if(ad)
            out <= from_a + bus_d;
        if(sub)
            out <= from_a - bus_d;
    
    assign to_b = (ad || sub) ? out : 8'bz;

    end

endmodule

module controller(inout [7:0] bus_i, inout [7:0] bus_d, output reg pc_a, output reg mar_a, output reg ir_a, input [3:0] ir_i, input clk, input reset);
    reg [2:0] stagecount = 0;
    reg aflag = 0;

    // CODES

    parameter OP_LDA = 4'b1000;
    parameter OP_LDB = 4'b0100;
    parameter OP_ADD = 4'b0010;
    parameter OP_SUB = 4'b0001;
    parameter OP_MUL = 4'b1100;
    parameter OP_DIV = 4'b1010;
    parameter OP_JMP = 4'b1001;
    parameter OP_HLT = 4'b1111;


    // Control word: pc_a, mar_a, ir_a

    always @(posedge clk) begin
        stagecount = stagecount + 1;
        if (stagecount == 4) begin
            pc_a = 0;
            mar_a = 0;
            ir_a = 0;
            //ctrl_wd = 000;
            stagecount = 0;
        end
        // First 3 stages are always the same
        if (stagecount == 1) begin
            pc_a = 1;
            mar_a = 1;
            ir_a = 0;
            //ctrl_wd = 110;
        end
        if (stagecount == 2) begin
            pc_a = 0;
            mar_a = 1;
            ir_a = 0;
            //ctrl_wd = 010;
        end
        if (stagecount == 3) begin
            pc_a = 0;
            mar_a = 0;
            ir_a = 1;
            //ctrl_wd = 001;
        end
        if (ir_i == OP_LDA) begin
            if (stagecount == 4) begin
            end
        end 


        
    end


endmodule

module top(output [7:0] bus_i, input clk, input reset);
    reg pc_a = 0;
    reg mar_a = 0;
    reg ir_a = 0;
    // RAM flags
    reg in_b = 0;
    reg out_b = 0;
    reg in_a = 0;
    reg out_a = 0;
    //-----
    // Register flags
    reg a_out = 0;
    //----
    reg out_bus = 0;
    reg [3:0] ir_i;
    reg [7:0] bus_d;
    wire [3:0] to_ram;
    wire [7:0] to_ir;
    wire [7:0] to_a;
    wire [7:0] to_b;

    controller control(.bus_i(bus_i), .bus_d(bus_d), .pc_a(pc_a), .mar_a(mar_a), .ir_a(ir_a), .ir_i(ir_i), .clk(clk), .reset(reset));

    program_counter counter(.bus_i(bus_i), .clk(clk), .reset(reset), .pc_a(pc_a));

    mar mar(.bus_i(bus_i), .to_ram(to_ram), .clk(clk), .reset(reset), .mar_a(mar_a));

    ram ram(.to_ir(to_ir), .to_a(to_a), .to_b(to_b), .mar_in(to_ram), .in_b(in_b), .out_b(out_b), .in_a(in_a), .out_a(out_a), .clk(clk), .reset(reset));

    instruction_register ir(.bus_i(bus_i), .from_ram(to_ir), .to_ctrl(ir_i), .clk(clk), .reset(reset), .ir_a(ir_a));

    register areg(.bus_d(bus_d), .from_ram(to_a), .clk(clk), .ram_in(out_a), .out_b(a_out));




endmodule

Waveform.vcd
$version Generated by VerilatedVcd $end
$timescale 1ps $end

 $scope module TOP $end
  $var wire  8 3 bus_i [7:0] $end
  $var wire  1 4 clk $end
  $var wire  1 5 reset $end
  $scope module top $end
   $var wire  1 6 a_out $end
   $var wire  8 7 bus_d [7:0] $end
   $var wire  8 3 bus_i [7:0] $end
   $var wire  1 4 clk $end
   $var wire  1 6 in_a $end
   $var wire  1 6 in_b $end
   $var wire  1 % ir_a $end
   $var wire  4 & ir_i [3:0] $end
   $var wire  1 $ mar_a $end
   $var wire  1 6 out_a $end
   $var wire  1 6 out_b $end
   $var wire  1 6 out_bus $end
   $var wire  1 # pc_a $end
   $var wire  1 5 reset $end
   $var wire  8 7 to_a [7:0] $end
   $var wire  8 7 to_b [7:0] $end
   $var wire  8 ( to_ir [7:0] $end
   $var wire  4 ' to_ram [3:0] $end
   $scope module areg $end
    $var wire  8 8 areg [7:0] $end
    $var wire  8 7 bus_d [7:0] $end
    $var wire  1 4 clk $end
    $var wire  8 7 from_ram [7:0] $end
    $var wire  1 6 out_b $end
    $var wire  1 6 ram_in $end
   $upscope $end
   $scope module control $end
    $var wire  4 ; OP_ADD [3:0] $end
    $var wire  4 > OP_DIV [3:0] $end
    $var wire  4 @ OP_HLT [3:0] $end
    $var wire  4 ? OP_JMP [3:0] $end
    $var wire  4 9 OP_LDA [3:0] $end
    $var wire  4 : OP_LDB [3:0] $end
    $var wire  4 = OP_MUL [3:0] $end
    $var wire  4 < OP_SUB [3:0] $end
    $var wire  1 6 aflag $end
    $var wire  8 7 bus_d [7:0] $end
    $var wire  8 3 bus_i [7:0] $end
    $var wire  1 4 clk $end
    $var wire  1 % ir_a $end
    $var wire  4 & ir_i [3:0] $end
    $var wire  1 $ mar_a $end
    $var wire  1 # pc_a $end
    $var wire  1 5 reset $end
    $var wire  3 ) stagecount [2:0] $end
   $upscope $end
   $scope module counter $end
    $var wire  8 3 bus_i [7:0] $end
    $var wire  1 4 clk $end
    $var wire  4 * pc [3:0] $end
    $var wire  1 # pc_a $end
    $var wire  1 5 reset $end
   $upscope $end
   $scope module ir $end
    $var wire  8 3 bus_i [7:0] $end
    $var wire  1 4 clk $end
    $var wire  8 ( from_ram [7:0] $end
    $var wire  4 + instruction [3:0] $end
    $var wire  1 % ir_a $end
    $var wire  1 5 reset $end
    $var wire  4 & to_ctrl [3:0] $end
   $upscope $end
   $scope module mar $end
    $var wire  4 , address [3:0] $end
    $var wire  8 3 bus_i [7:0] $end
    $var wire  1 4 clk $end
    $var wire  1 $ mar_a $end
    $var wire  1 5 reset $end
    $var wire  4 ' to_ram [3:0] $end
   $upscope $end
   $scope module ram $end
    $var wire  1 4 clk $end
    $var wire  1 6 in_a $end
    $var wire  1 6 in_b $end
    $var wire  8 2 index [7:0] $end
    $var wire  4 ' mar_in [3:0] $end
    $var wire 129 - mem [128:0] $end
    $var wire  8 ( out [7:0] $end
    $var wire  1 6 out_a $end
    $var wire  1 6 out_b $end
    $var wire  1 5 reset $end
    $var wire  8 7 to_a [7:0] $end
    $var wire  8 7 to_b [7:0] $end
    $var wire  8 ( to_ir [7:0] $end
   $upscope $end
  $upscope $end
 $upscope $end
$enddefinitions $end


#0
0#
0$
0%
b0000 &
b0000 '
b00000000 (
b000 )
b0000 *
b0000 +
b0000 ,
b000000000000000000000000000000000000000000000000000000000000000000000000000000000000000000000000000000000000000000000000000000000 -
b00000000 2
b00000000 3
14
05
06
b00000000 7
b00000000 8
b1000 9
b0100 :
b0010 ;
b0001 <
b1100 =
b1010 >
b1001 ?
b1111 @
#1
04
#2
1#
1$
b001 )
b0001 *
b000000000000000000000000000000000000000000000000000000000000000000000000000000000100010010000000100000010111111110100000100000000 -
b00000001 3
14
#3
04
#4
0#
b0001 '
b010 )
b0001 ,
b00000000 3
14
#5
04
#6
0$
1%
b0000 '
b011 )
14
#7
04
#8
0%
b000 )
14
#9
04
#10
1#
1$
b001 )
b0010 *
b0000 ,
b00001000 2
b00000010 3
14
#11
04
#12
0#
b0010 '
b01000001 (
b010 )
b0010 ,
b00000000 2
b00000000 3
14
#13
04
#14
0$
1%
b0100 &
b0000 '
b00000000 (
b011 )
b0100 +
14
#15
04
#16
0%
b0000 &
b000 )
14
#17
04
#18
1#
1$
b001 )
b0011 *
b0000 ,
b00010000 2
b00000011 3
14
#19
04
#20
0#
b0011 '
b11111111 (
b010 )
b0011 ,
b00000000 2
b00000000 3
14
#21
04
#22
0$
1%
b1111 &
b0000 '
b00000000 (
b011 )
b1111 +
14
#23
04
#24
0%
b0000 &
b000 )
14
#25
04
#26
1#
1$
b001 )
b0100 *
b0000 ,
b00011000 2
b00000100 3
14
#27
04
#28
0#
b0100 '
b00000010 (
b010 )
b0100 ,
b00000000 2
b00000000 3
14
#29
04
#30
0$
1%
b0000 '
b00000000 (
b011 )
b0000 +
14
#31
04
#32
0%
b000 )
14
#33
04
#34
1#
1$
b001 )
b0101 *
b0000 ,
b00100000 2
b00000101 3
14
#35
04
#36
0#
b0101 '
b00000001 (
b010 )
b0101 ,
b00000000 2
b00000000 3
14
#37
04
#38
0$
1%
b0000 '
b00000000 (
b011 )
14
#39
04
#40
0%
b000 )
14
#41
04
#42
1#
1$
b001 )
b0110 *
b0000 ,
b00101000 2
b00000110 3
14
#43
04
#44
0#
b0110 '
b10001001 (
b010 )
b0110 ,
b00000000 2
b00000000 3
14
#45
04
#46
0$
1%
b1000 &
b0000 '
b00000000 (
b011 )
b1000 +
14
#47
04
#48
0%
b0000 &
b000 )
14
#49
04
#50
1#
1$
b001 )
b0111 *
b0000 ,
b00110000 2
b00000111 3
14
#51
04
#52
0#
b0111 '
b010 )
b0111 ,
b00000000 2
b00000000 3
14
#53
04
#54
0$
1%
b0000 '
b011 )
b0000 +
14
#55
04
#56
0%
b000 )
14
#57
04
#58
1#
1$
b001 )
b1000 *
b0000 ,
b00111000 2
b00001000 3
14
#59
04
#60
0#
b1000 '
b010 )
b1000 ,
b00000000 2
b00000000 3
14
#61
04
#62
0$
1%
b0000 '
b011 )
14
#63
04
#64
0%
b000 )
14
#65
04
#66
1#
1$
b001 )
b1001 *
b0000 ,
b01000000 2
b00001001 3
14
#67
04
#68
0#
b1001 '
b010 )
b1001 ,
b00000000 2
b00000000 3
14
#69
04
#70
0$
1%
b0000 '
b011 )
14
#71
04
#72
0%
b000 )
14
#73
04
#74
1#
1$
b001 )
b1010 *
b0000 ,
b01001000 2
b00001010 3
14
#75
04
#76
0#
b1010 '
b010 )
b1010 ,
b00000000 2
b00000000 3
14
#77
04
#78
0$
1%
b0000 '
b011 )
14
#79
04
#80
0%
b000 )
14
#81
04
#82
1#
1$
b001 )
b1011 *
b0000 ,
b01010000 2
b00001011 3
14
#83
04
#84
0#
b1011 '
b010 )
b1011 ,
b00000000 2
b00000000 3
14
#85
04
#86
0$
1%
b0000 '
b011 )
14
#87
04
#88
0%
b000 )
14
#89
04
#90
1#
1$
b001 )
b1100 *
b0000 ,
b01011000 2
b00001100 3
14
#91
04
#92
0#
b1100 '
b010 )
b1100 ,
b00000000 2
b00000000 3
14
#93
04
#94
0$
1%
b0000 '
b011 )
14
#95
04
#96
0%
b000 )
14
#97
04
#98
1#
1$
b001 )
b1101 *
b0000 ,
b01100000 2
b00001101 3
14
