cpuf.v
// LITTLE ENDIAN
// First four bytes are instruction, last four address
// verilator lint_off BLKANDNBLK

// INSTRUCTIONS
// [_ _ _ _][_ _ _ _]
//   Instr.   Addr.
// OP_LDA : 1000 => Load value at address into register A
// OP_LDB : 0100 => Load value at address into register B
// OP_ADD : 0010 => Add values in Register A and B and dump in accumulator
// OP_SUB : 0001 => Subtract value in B from register A and dump in accumulator
// OP_JMP : 1001 => Jump to instruction at address
// OP_HLT : 1111 => Halt 
// OP_WRT : 1010 => Write accumulator contents to RAM
// OP_DMA : 1101 => Dump A register into data bus
// OP_DMB : 1011 => Dump B register into data bus

// STUFF ON Instruction Bus
module program_counter(output reg [7:0] bus_i, input clk, input reset, input pc_a, input [3:0] from_ir, input jmp);
    
    reg [3:0] pc;
    
    always @(posedge clk) begin
        if (reset)
            pc <= 0;
        else if (pc_a)
            pc <= pc + 1; 
        else if (jmp)
            pc <= from_ir - 4'b0001;

        if (pc_a)
         bus_i <= {4'b0,pc};
    end

    //assign bus_i = (pc_a) ? {4'bz,pc} : 8'bz;

endmodule

module instruction_register(inout [7:0] bus_i, input [7:0] from_ram, output [3:0] to_ctrl, output [3:0] to_ram, input clk, input reset, input ir_a);

    reg [3:0] instruction;
    reg [3:0] address; // Address in instruction

    always @(posedge clk) begin
        if (reset) begin
            instruction <= 0;
        end
        else if (ir_a) begin
            address <= from_ram[3:0];
            instruction <= from_ram[7:4];
        end 
    end

    //assign bus_i = (out_b) ? {instruction,4'bz} : 8'bz;
    assign to_ctrl = (1) ? instruction : 4'bz;
    assign to_ram = address;

endmodule

module mar(inout [7:0] bus_i, output [3:0] to_ram, input [3:0] from_ir, input clk, input reset, input mar_a, input jmp);

    reg [3:0] address;
    reg [3:0] offset;

    always @(posedge clk) begin
        if (mar_a) begin
            address <= bus_i[3:0];
        end
        else if (jmp) begin
            address <= from_ir;
            
        end
        //else
        //    address <= from_ir;
    end

    //assign to_ram = (mar_a) ? address : 4'bz;
    assign to_ram = address;
endmodule
// -----

// RAM
module ram(output [7:0] to_ir, inout [7:0] to_a, inout [7:0] to_b, inout [7:0] to_c, input [3:0] mar_in, input [3:0] address_ir, input in_c, input in_b, input out_b, input in_a, input out_a, input clk, input reset);

    reg [128:0] mem;
    reg [7:0] index_ir;
    reg [7:0] index_reg;
    reg [7:0] out_reg;
    reg [7:0] out_ir;

    always @(posedge clk) begin
        // Contents of RAM, including data and the program itself
        mem[7:0] <= 8'b00000100;
        mem[15:8] <= 8'b10000110; //LDA 0110
        mem[23:16] <= 8'b01000101; //LDB 0111
        mem[31:24] <= 8'b00100001; //ADD
        mem[39:32] <= 8'b10010111; //JMP 0111
        mem[47:40] <= 8'b00001110;
        mem[55:48] <= 8'b00001100;
        mem[63:56] <= 8'b10000110; //LDA 0101
        mem[71:64] <= 8'b10000110; //LDA 0110
        mem[79:72] <= 8'b10100110; //WRT
        mem[87:80] <= 8'b10001111; //LDA 1000
        mem[95:88] <= 8'b10111111; //DMA
        mem[103:96] <= 8'b11111111; //HLT
        
        if(reset) begin
            //index <= 0;
            //out <= 0;
        end
        else if(in_c) begin
            mem[127:120] <= to_c;
        end
        else if(in_a) begin
            mem[119:112] <= to_a;
        end


        index_ir <= mar_in * 8;
        out_ir <= mem[index_ir +: 8];

        index_reg <= out_ir[3:0] * 8;
        out_reg <= mem[index_reg +: 8];

    end

    assign to_a = (out_a) ? out_reg : 8'bz;
    assign to_b = (out_b) ? out_reg : 8'bz;
    assign to_ir = out_ir;

endmodule
// Stuff on data bus

module register(output [7:0] to_out, inout [7:0] bus_d, input [7:0] from_inp, input clk, input inp_in, input out_o, input out_b);

    reg [7:0] areg;

    always @(negedge clk) begin
        if (inp_in)
            areg <= from_inp;
    end

    assign bus_d = (out_b) ? areg : 8'bz;
    assign to_out = areg;


endmodule

module alu(output reg [7:0] to_acc, inout [7:0] bus_d, input [7:0] from_a, input [7:0] from_b, input clk, input ad, input sub);
    reg [7:0] out;
    
    always @(posedge clk) begin
        if(ad)
            out <= from_a + from_b;
        if(sub)
            out <= from_a - from_b;
    
    assign to_acc = (1) ? out : 8'bz; //ad || sub

    end

endmodule

module controller(inout [7:0] bus_i, inout [7:0] bus_d, output reg pc_a, output reg mar_a, output reg ir_a, output reg in_a, output reg out_a, output reg in_b, output reg out_b, output reg ad, output reg sb, output reg jmp, output reg acc_out, output reg a_out_bus, output reg b_out_bus, input [3:0] ir_i, input clk, input reset);
    reg [2:0] stagecount = 0;
    reg aflag = 0;

    // CODES

    parameter OP_LDA = 4'b1000;
    parameter OP_LDB = 4'b0100;
    parameter OP_ADD = 4'b0010;
    parameter OP_SUB = 4'b0001;
    parameter OP_JMP = 4'b1001;
    parameter OP_HLT = 4'b1111;
    parameter OP_WRT = 4'b1010;
    parameter OP_DMA = 4'b1011;
    parameter OP_DMB = 4'b1101;


    // Control word: pc_a, mar_a, ir_a, in_a (input to ram), out_a (output from ram), in_b, out_b, ad, sb, jmp, acc_out, a_out_bus, b_out_bus

    always @(negedge clk) begin
        if (ir_i == OP_HLT) begin
            pc_a <= 0;
            mar_a <= 0;
            ir_a <= 0;
            in_a <= 0;
            out_a <= 0;
            in_b <= 0;
            out_b <= 0;
            ad <= 0;
            sb <= 0;
            jmp <= 0;
            acc_out <= 0;
        end
        else begin
            stagecount <= stagecount + 1;
            if (stagecount == 5) begin
                pc_a <= 0;
                mar_a <= 0;
                ir_a <= 0;
                in_a <= 0;
                out_a <= 0;
                in_b <= 0;
                out_b <= 0;
                ad <= 0;
                sb <= 0;
                jmp <= 0;
                acc_out <= 0;
                //a_out_bus <= 0;
                //b_out_bus <= 0;
                //ctrl_wd <= 000;
                stagecount <= 0;
            end
            // First 3 stages are always the same
            if (stagecount == 0) begin
                pc_a <= 1;
                mar_a <= 0; //0
                ir_a <= 0; //0
                in_a <= 0;
                out_a <= 0;
                in_b <= 0;
                out_b <= 0;
                ad <= 0;
                sb <= 0;
                jmp <= 0;
                acc_out <= 0;
                //a_out_bus <= 0;
                //b_out_bus <= 0;
                //ctrl_wd <= 110;
            end
            if (stagecount == 1) begin
                pc_a <= 0;
                mar_a <= 1;
                ir_a <= 0; //0
                in_a <= 0;
                out_a <= 0;
                in_b <= 0;
                out_b <= 0;
                jmp <= 0;
                acc_out <= 0;
                //a_out_bus <= 0;
                //b_out_bus <= 0;
                //ctrl_wd <= 010;
            end
            if (stagecount == 2) begin
                pc_a <= 0;
                mar_a <= 0;
                ir_a <= 1; //1
                in_a <= 0;
                out_a <= 0;
                in_b <= 0;
                out_b <= 0;
                ad <= 0;
                sb <= 0;
                jmp <= 0;
                acc_out <= 0;
                //a_out_bus <= 0;
                //b_out_bus <= 0;
                //ctrl_wd <= 001;
            end
            if (ir_i == OP_JMP) begin
                if (stagecount == 3) begin
                    pc_a <= 0;
                    mar_a <= 0;
                    ir_a <= 0;
                    in_a <= 0;
                    out_a <= 0;
                    in_b <= 0;
                    out_b <= 0;
                    ad <= 0;
                    sb <= 0;
                    jmp <= 1;
                    acc_out <= 0;
                    a_out_bus <= 0;
                    b_out_bus <= 0;
                end
                if (stagecount == 4) begin
                    pc_a <= 0;
                    mar_a <= 0;
                    ir_a <= 0;
                    in_a <= 0;
                    out_a <= 0;
                    in_b <= 0;
                    out_b <= 0;
                    ad <= 0;
                    sb <= 0;
                    jmp <= 0;
                    acc_out <= 0;
                    a_out_bus <= 0;
                    b_out_bus <= 0;
                end

            end
            else begin
                if (ir_i == OP_LDA) begin
                    if (stagecount == 3) begin
                        pc_a <= 0;
                        mar_a <= 0;
                        ir_a <= 0;
                        in_a <= 0;
                        out_a <= 1;
                        in_b <= 0;
                        out_b <= 0;
                        ad <= 0;
                        sb <= 0;
                        jmp <= 0;
                        acc_out <= 0;
                        a_out_bus <= 0;
                        b_out_bus <= 0;
                    end
                    if (stagecount == 4) begin
                        pc_a <= 0;
                        mar_a <= 0;
                        ir_a <= 0;
                        in_a <= 0;
                        out_a <= 0;
                        in_b <= 0;
                        out_b <= 0;
                        ad <= 0;
                        sb <= 0;
                        jmp <= 0;
                        acc_out <= 0;
                        a_out_bus <= 0;
                        b_out_bus <= 0;
                    end
                end 
                else if (ir_i == OP_LDB) begin
                    if (stagecount == 3) begin
                        pc_a <= 0;
                        mar_a <= 0;
                        ir_a <= 0;
                        in_a <= 0;
                        out_a <= 0;
                        in_b <= 0;
                        out_b <= 1;
                        ad <= 0;
                        sb <= 0;
                        jmp <= 0;
                        acc_out <= 0;
                        a_out_bus <= 0;
                        b_out_bus <= 0;
                    end
                    if (stagecount == 4) begin
                        pc_a <= 0;
                        mar_a <= 0;
                        ir_a <= 0;
                        in_a <= 0;
                        out_a <= 0;
                        in_b <= 0;
                        out_b <= 0;
                        ad <= 0;
                        sb <= 0;
                        jmp <= 0;
                        acc_out <= 0;
                        a_out_bus <= 0;
                        b_out_bus <= 0;
                    end
                end
                else if (ir_i == OP_ADD) begin
                    if (stagecount == 3) begin
                        pc_a <= 0;
                        mar_a <= 0;
                        ir_a <= 0;
                        in_a <= 0;
                        out_a <= 0;
                        in_b <= 0;
                        out_b <= 0;
                        ad <= 1;
                        sb <= 0;
                        jmp <= 0;
                        acc_out <= 0;
                        a_out_bus <= 0;
                        b_out_bus <= 0;
                    end
                    if (stagecount == 4) begin
                        pc_a <= 0;
                        mar_a <= 0;
                        ir_a <= 0;
                        in_a <= 0;
                        out_a <= 0;
                        in_b <= 0;
                        out_b <= 0;
                        ad <= 0;
                        sb <= 0;
                        jmp <= 0;
                        acc_out <= 0;
                        a_out_bus <= 0;
                        b_out_bus <= 0;
                    end
                end
                else if (ir_i == OP_SUB) begin
                    if (stagecount == 3) begin
                        pc_a <= 0;
                        mar_a <= 0;
                        ir_a <= 0;
                        in_a <= 0;
                        out_a <= 0;
                        in_b <= 0;
                        out_b <= 0;
                        ad <= 0;
                        sb <= 1;
                        jmp <= 0;
                        acc_out <= 0;
                        a_out_bus <= 0;
                        b_out_bus <= 0;
                    end
                    if (stagecount == 4) begin
                        pc_a <= 0;
                        mar_a <= 0;
                        ir_a <= 0;
                        in_a <= 0;
                        out_a <= 0;
                        in_b <= 0;
                        out_b <= 0;
                        ad <= 0;
                        sb <= 0;
                        jmp <= 0;
                        acc_out <= 0;
                        a_out_bus <= 0;
                        b_out_bus <= 0;
                    end
                end
                else if (ir_i == OP_WRT) begin
                    if (stagecount == 3) begin
                        pc_a <= 0;
                        mar_a <= 0;
                        ir_a <= 0;
                        in_a <= 0;
                        out_a <= 0;
                        in_b <= 0;
                        out_b <= 0;
                        ad <= 0;
                        sb <= 0;
                        jmp <= 0;
                        acc_out <= 1;
                        a_out_bus <= 0;
                        b_out_bus <= 0;
                    end
                    if (stagecount == 4) begin
                        pc_a <= 0;
                        mar_a <= 0;
                        ir_a <= 0;
                        in_a <= 0;
                        out_a <= 0;
                        in_b <= 0;
                        out_b <= 0;
                        ad <= 0;
                        sb <= 0;
                        jmp <= 0;
                        acc_out <= 0;
                        a_out_bus <= 0;
                        b_out_bus <= 0;
                    end
                end
                else if (ir_i == OP_DMA) begin
                    if (stagecount == 3) begin
                        pc_a <= 0;
                        mar_a <= 0;
                        ir_a <= 0;
                        in_a <= 0;
                        out_a <= 0;
                        in_b <= 0;
                        out_b <= 0;
                        ad <= 0;
                        sb <= 0;
                        jmp <= 0;
                        acc_out <= 0;
                        a_out_bus <= 1;
                        b_out_bus <= 0;
                    end
                    if (stagecount == 4) begin
                        pc_a <= 0;
                        mar_a <= 0;
                        ir_a <= 0;
                        in_a <= 0;
                        out_a <= 0;
                        in_b <= 0;
                        out_b <= 0;
                        ad <= 0;
                        sb <= 0;
                        jmp <= 0;
                        acc_out <= 0;
                        a_out_bus <= 1;
                        b_out_bus <= 0;
                    end
                end
                else if (ir_i == OP_DMB) begin
                    if (stagecount == 3) begin
                        pc_a <= 0;
                        mar_a <= 0;
                        ir_a <= 0;
                        in_a <= 0;
                        out_a <= 0;
                        in_b <= 0;
                        out_b <= 0;
                        ad <= 0;
                        sb <= 0;
                        jmp <= 0;
                        acc_out <= 0;
                        a_out_bus <= 0;
                        b_out_bus <= 1;
                    end
                    if (stagecount == 4) begin
                        pc_a <= 0;
                        mar_a <= 0;
                        ir_a <= 0;
                        in_a <= 0;
                        out_a <= 0;
                        in_b <= 0;
                        out_b <= 0;
                        ad <= 0;
                        sb <= 0;
                        jmp <= 0;
                        acc_out <= 0;
                        a_out_bus <= 0;
                        b_out_bus <= 1;
                    end
                end
                else begin
                    if (stagecount == 3) begin
                        pc_a <= 0;
                        mar_a <= 0;
                        ir_a <= 0;
                        in_a <= 0;
                        out_a <= 0;
                        in_b <= 0;
                        out_b <= 0;
                        ad <= 0;
                        sb <= 0;
                        jmp <= 0;
                        acc_out <= 0;
                        a_out_bus <= 0;
                        b_out_bus <= 0;
                    end
                    if (stagecount == 4) begin
                        pc_a <= 0;
                        mar_a <= 0;
                        ir_a <= 0;
                        in_a <= 0;
                        out_a <= 0;
                        in_b <= 0;
                        out_b <= 0;
                        ad <= 0;
                        sb <= 0;
                        jmp <= 0;
                        acc_out <= 0;
                        a_out_bus <= 0;
                        b_out_bus <= 0;
                    end
                end
            end
        end
    end
endmodule

module cpu(output [7:0] bus_i, output [7:0] bus_d, input clk, input reset);
    reg pc_a = 0;
    reg mar_a = 0;
    reg ir_a = 0;
    reg jmp = 0;
    // RAM flags
    reg in_b = 0;
    reg out_b = 0;
    reg in_a = 0;
    reg out_a = 0;
    //-----
    // accumulator
    reg c_out_acc = 1; //calculator out
    reg acc_out = 0;
    reg ad = 0;
    reg sb = 0;
    // Register flags (BUS OUT)
    reg a_out = 0;
    reg b_out = 0;
    //----
    reg out_bus = 0;
    reg [3:0] ir_i;
    //reg [7:0] bus_d;
    //reg [7:0] bus_i;
    wire [3:0] to_ram;
    wire [7:0] to_ir;
    wire [7:0] to_a;
    wire [7:0] to_b;
    wire [7:0] to_acc;
    wire [7:0] a_calc;
    wire [7:0] b_calc;
    wire [7:0] c_calc;
    wire [3:0] address_ir;

    controller control(.bus_i(bus_i), .bus_d(bus_d), .pc_a(pc_a), .mar_a(mar_a), .ir_a(ir_a), .in_a(in_a), .out_a(out_a), .in_b(in_b), .out_b(out_b), .ad(ad), .sb(sb), .jmp(jmp), .acc_out(acc_out), .a_out_bus(a_out), .b_out_bus(b_out), .ir_i(ir_i), .clk(clk), .reset(reset));

    program_counter counter(.bus_i(bus_i), .clk(clk), .reset(reset), .pc_a(pc_a), .from_ir(address_ir), .jmp(jmp));

    mar mar(.bus_i(bus_i), .to_ram(to_ram), .from_ir(address_ir), .clk(clk), .reset(reset), .mar_a(mar_a), .jmp(jmp));

    ram ram(.to_ir(to_ir), .to_a(to_a), .to_b(to_b), .to_c(c_calc), .mar_in(to_ram), .address_ir(address_ir), .in_c(acc_out), .in_b(in_b), .out_b(out_b), .in_a(in_a), .out_a(out_a), .clk(clk), .reset(reset));

    instruction_register ir(.bus_i(bus_i), .from_ram(to_ir), .to_ctrl(ir_i), .to_ram(address_ir), .clk(clk), .reset(reset), .ir_a(ir_a));

    register areg(.to_out(a_calc), .bus_d(bus_d), .from_inp(to_a), .clk(clk), .inp_in(out_a), .out_o(0), .out_b(a_out));
    
    //register breg(.to_c(b_calc), .bus_d(bus_d), .from_ram(to_b), .clk(clk), .ram_in(out_b), .out_b(b_out));
    register breg(.to_out(b_calc), .bus_d(bus_d), .from_inp(to_b), .clk(clk), .inp_in(out_b), .out_o(0), .out_b(b_out));

    register accumulator(.to_out(c_calc), .bus_d(bus_d), .from_inp(to_acc), .clk(clk), .inp_in(c_out_acc), .out_o(acc_out), .out_b(0));

    alu alu(.to_acc(to_acc), .bus_d(bus_d), .from_a(a_calc), .from_b(b_calc), .clk(clk), .ad(ad), .sub(sb));

endmodule

module top(output [7:0] led_1, output [7:0] led_2, input clk, input reset);

    cpu cpu(.bus_i(led_2), .bus_d(led_1), .clk(clk), .reset(reset));

endmodule

Waveform.vcd
$version Generated by VerilatedVcd $end
$timescale 1ps $end

 $scope module TOP $end
  $var wire  1 F clk $end
  $var wire  8 D led_1 [7:0] $end
  $var wire  8 E led_2 [7:0] $end
  $var wire  1 G reset $end
  $scope module top $end
   $var wire  1 F clk $end
   $var wire  8 D led_1 [7:0] $end
   $var wire  8 E led_2 [7:0] $end
   $var wire  1 G reset $end
   $scope module cpu $end
    $var wire  8 0 a_calc [7:0] $end
    $var wire  1 . a_out $end
    $var wire  1 + acc_out $end
    $var wire  1 , ad $end
    $var wire  4 8 address_ir [3:0] $end
    $var wire  8 1 b_calc [7:0] $end
    $var wire  1 / b_out $end
    $var wire  8 D bus_d [7:0] $end
    $var wire  8 E bus_i [7:0] $end
    $var wire  8 2 c_calc [7:0] $end
    $var wire  1 J c_out_acc $end
    $var wire  1 F clk $end
    $var wire  1 ) in_a $end
    $var wire  1 ' in_b $end
    $var wire  1 % ir_a $end
    $var wire  4 4 ir_i [3:0] $end
    $var wire  1 & jmp $end
    $var wire  1 $ mar_a $end
    $var wire  1 * out_a $end
    $var wire  1 ( out_b $end
    $var wire  1 K out_bus $end
    $var wire  1 # pc_a $end
    $var wire  1 G reset $end
    $var wire  1 - sb $end
    $var wire  8 H to_a [7:0] $end
    $var wire  8 7 to_acc [7:0] $end
    $var wire  8 I to_b [7:0] $end
    $var wire  8 6 to_ir [7:0] $end
    $var wire  4 5 to_ram [3:0] $end
    $scope module accumulator $end
     $var wire  8 2 areg [7:0] $end
     $var wire  8 D bus_d [7:0] $end
     $var wire  1 F clk $end
     $var wire  8 7 from_inp [7:0] $end
     $var wire  1 J inp_in $end
     $var wire  1 K out_b $end
     $var wire  1 + out_o $end
     $var wire  8 2 to_out [7:0] $end
    $upscope $end
    $scope module alu $end
     $var wire  1 , ad $end
     $var wire  8 D bus_d [7:0] $end
     $var wire  1 F clk $end
     $var wire  8 0 from_a [7:0] $end
     $var wire  8 1 from_b [7:0] $end
     $var wire  8 9 out [7:0] $end
     $var wire  1 - sub $end
     $var wire  8 7 to_acc [7:0] $end
    $upscope $end
    $scope module areg $end
     $var wire  8 0 areg [7:0] $end
     $var wire  8 D bus_d [7:0] $end
     $var wire  1 F clk $end
     $var wire  8 H from_inp [7:0] $end
     $var wire  1 * inp_in $end
     $var wire  1 . out_b $end
     $var wire  1 K out_o $end
     $var wire  8 0 to_out [7:0] $end
    $upscope $end
    $scope module breg $end
     $var wire  8 1 areg [7:0] $end
     $var wire  8 D bus_d [7:0] $end
     $var wire  1 F clk $end
     $var wire  8 I from_inp [7:0] $end
     $var wire  1 ( inp_in $end
     $var wire  1 / out_b $end
     $var wire  1 K out_o $end
     $var wire  8 1 to_out [7:0] $end
    $upscope $end
    $scope module control $end
     $var wire  4 N OP_ADD [3:0] $end
     $var wire  4 S OP_DMA [3:0] $end
     $var wire  4 T OP_DMB [3:0] $end
     $var wire  4 Q OP_HLT [3:0] $end
     $var wire  4 P OP_JMP [3:0] $end
     $var wire  4 L OP_LDA [3:0] $end
     $var wire  4 M OP_LDB [3:0] $end
     $var wire  4 O OP_SUB [3:0] $end
     $var wire  4 R OP_WRT [3:0] $end
     $var wire  1 . a_out_bus $end
     $var wire  1 + acc_out $end
     $var wire  1 , ad $end
     $var wire  1 K aflag $end
     $var wire  1 / b_out_bus $end
     $var wire  8 D bus_d [7:0] $end
     $var wire  8 E bus_i [7:0] $end
     $var wire  1 F clk $end
     $var wire  1 ) in_a $end
     $var wire  1 ' in_b $end
     $var wire  1 % ir_a $end
     $var wire  4 4 ir_i [3:0] $end
     $var wire  1 & jmp $end
     $var wire  1 $ mar_a $end
     $var wire  1 * out_a $end
     $var wire  1 ( out_b $end
     $var wire  1 # pc_a $end
     $var wire  1 G reset $end
     $var wire  1 - sb $end
     $var wire  3 3 stagecount [2:0] $end
    $upscope $end
    $scope module counter $end
     $var wire  8 : bus_i [7:0] $end
     $var wire  1 F clk $end
     $var wire  4 8 from_ir [3:0] $end
     $var wire  1 & jmp $end
     $var wire  4 ; pc [3:0] $end
     $var wire  1 # pc_a $end
     $var wire  1 G reset $end
    $upscope $end
    $scope module ir $end
     $var wire  4 8 address [3:0] $end
     $var wire  8 E bus_i [7:0] $end
     $var wire  1 F clk $end
     $var wire  8 6 from_ram [7:0] $end
     $var wire  4 4 instruction [3:0] $end
     $var wire  1 % ir_a $end
     $var wire  1 G reset $end
     $var wire  4 4 to_ctrl [3:0] $end
     $var wire  4 8 to_ram [3:0] $end
    $upscope $end
    $scope module mar $end
     $var wire  4 5 address [3:0] $end
     $var wire  8 E bus_i [7:0] $end
     $var wire  1 F clk $end
     $var wire  4 8 from_ir [3:0] $end
     $var wire  1 & jmp $end
     $var wire  1 $ mar_a $end
     $var wire  4 U offset [3:0] $end
     $var wire  1 G reset $end
     $var wire  4 5 to_ram [3:0] $end
    $upscope $end
    $scope module ram $end
     $var wire  4 8 address_ir [3:0] $end
     $var wire  1 F clk $end
     $var wire  1 ) in_a $end
     $var wire  1 ' in_b $end
     $var wire  1 + in_c $end
     $var wire  8 A index_ir [7:0] $end
     $var wire  8 B index_reg [7:0] $end
     $var wire  4 5 mar_in [3:0] $end
     $var wire 129 < mem [128:0] $end
     $var wire  1 * out_a $end
     $var wire  1 ( out_b $end
     $var wire  8 6 out_ir [7:0] $end
     $var wire  8 C out_reg [7:0] $end
     $var wire  1 G reset $end
     $var wire  8 H to_a [7:0] $end
     $var wire  8 I to_b [7:0] $end
     $var wire  8 2 to_c [7:0] $end
     $var wire  8 6 to_ir [7:0] $end
    $upscope $end
   $upscope $end
  $upscope $end
 $upscope $end
$enddefinitions $end


#0
0#
0$
0%
0&
0'
0(
0)
0*
0+
0,
0-
0.
0/
b00000000 0
b00000000 1
b00000000 2
b000 3
b0000 4
b0000 5
b00000000 6
b00000000 7
b0000 8
b00000000 9
b00000000 :
b0000 ;
b000000000000000000000000000000000000000000000000000000000000000000000000000000000000000000000000000000000000000000000000000000000 <
b00000000 A
b00000000 B
b00000000 C
b00000000 D
b00000000 E
1F
0G
b00000000 H
b00000000 I
1J
0K
b1000 L
b0100 M
b0010 N
b0001 O
b1001 P
b1111 Q
b1010 R
b1011 S
b1101 T
b0000 U
#1
1#
b001 3
0F
#2
b0001 ;
b000000000000000000000000011111111101111111000111110100110100001101000011000001100000011101001011100100001010001011000011000000100 <
1F
#3
0#
1$
b010 3
0F
#4
b00000100 6
b00000100 C
1F
#5
0$
1%
b011 3
0F
#6
b0100 8
b00100000 B
1F
#7
0%
b100 3
0F
#8
b10010111 C
1F
#9
b101 3
0F
#10
1F
#11
b000 3
0F
#12
1F
#13
1#
b001 3
0F
#14
b00000001 :
b0010 ;
b00000001 E
1F
#15
0#
1$
b010 3
0F
#16
b0001 5
1F
#17
0$
1%
b011 3
0F
#18
b00001000 A
1F
#19
0%
b100 3
0F
#20
b10000110 6
1F
#21
b101 3
0F
#22
b00110000 B
1F
#23
b000 3
0F
#24
b00001100 C
1F
#25
1#
b001 3
0F
#26
b00000010 :
b0011 ;
b00000010 E
1F
#27
0#
1$
b010 3
0F
#28
b0010 5
1F
#29
0$
1%
b011 3
0F
#30
b1000 4
b0110 8
b00010000 A
1F
#31
0%
1*
b100 3
0F
b00001100 H
#32
b01000101 6
1F
#33
0*
b00001100 0
b101 3
0F
b00000000 H
#34
b00101000 B
1F
#35
b000 3
0F
#36
b00001110 C
1F
#37
1#
b001 3
0F
#38
b00000011 :
b0100 ;
b00000011 E
1F
#39
0#
1$
b010 3
0F
#40
b0011 5
1F
#41
0$
1%
b011 3
0F
#42
b0100 4
b0101 8
b00011000 A
1F
#43
0%
1(
b100 3
0F
b00001110 I
#44
b00100001 6
1F
#45
0(
b00001110 1
b101 3
0F
b00000000 I
#46
b00001000 B
1F
#47
b000 3
0F
#48
b10000110 C
1F
#49
1#
b001 3
0F
#50
b00000100 :
b0101 ;
b00000100 E
1F
#51
0#
1$
b010 3
0F
#52
b0100 5
1F
#53
0$
1%
b011 3
0F
#54
b0010 4
b0001 8
b00100000 A
1F
#55
0%
1,
b100 3
0F
#56
b10010111 6
b00011010 9
1F
#57
0,
b101 3
0F
#58
b00011010 7
b00111000 B
1F
#59
b00011010 2
b000 3
0F
#60
1F
#61
1#
b001 3
0F
#62
b00000101 :
b0110 ;
b00000101 E
1F
#63
0#
1$
b010 3
0F
#64
b0101 5
1F
#65
0$
1%
b011 3
0F
#66
b1001 4
b0111 8
b00101000 A
1F
#67
0%
1&
b100 3
0F
#68
b0111 5
b00001110 6
1F
#69
0&
b101 3
0F
#70
b00111000 A
b01110000 B
1F
#71
b000 3
0F
#72
b10000110 6
b00000000 C
1F
#73
1#
b001 3
0F
#74
b00000110 :
b0111 ;
b00110000 B
b00000110 E
1F
#75
0#
1$
b010 3
0F
#76
b0110 5
b00001100 C
1F
#77
0$
1%
b011 3
0F
#78
b1000 4
b0110 8
b00110000 A
1F
#79
0%
1*
b100 3
0F
b00001100 H
#80
b00001100 6
1F
#81
0*
b101 3
0F
b00000000 H
#82
b01100000 B
1F
#83
b000 3
0F
#84
b11111111 C
1F
#85
1#
b001 3
0F
#86
b00000111 :
b1000 ;
b00000111 E
1F
#87
0#
1$
b010 3
0F
#88
b0111 5
1F
#89
0$
1%
b011 3
0F
#90
b0000 4
b1100 8
b00111000 A
1F
#91
0%
b100 3
0F
#92
b10000110 6
1F
#93
b101 3
0F
#94
b00110000 B
1F
#95
b000 3
0F
#96
b00001100 C
1F
#97
1#
b001 3
0F
#98
b00001000 :
b1001 ;
b00001000 E
1F
#99
0#
1$
b010 3
0F
#100
b1000 5
1F
#101
0$
1%
b011 3
0F
#102
b1000 4
b0110 8
b01000000 A
1F
#103
0%
1*
b100 3
0F
b00001100 H
#104
1F
#105
0*
b101 3
0F
b00000000 H
#106
1F
#107
b000 3
0F
#108
1F
#109
1#
b001 3
0F
#110
b00001001 :
b1010 ;
b00001001 E
1F
#111
0#
1$
b010 3
0F
#112
b1001 5
1F
#113
0$
1%
b011 3
0F
#114
b01001000 A
1F
#115
0%
1*
b100 3
0F
b00001100 H
#116
b10100110 6
1F
#117
0*
b101 3
0F
b00000000 H
#118
1F
#119
b000 3
0F
#120
1F
#121
1#
b001 3
0F
#122
b00001010 :
b1011 ;
b00001010 E
1F
#123
0#
1$
b010 3
0F
#124
b1010 5
1F
#125
0$
1%
b011 3
0F
#126
b1010 4
b01010000 A
1F
#127
0%
1+
b100 3
0F
#128
b10001111 6
b000011010000000000000000011111111101111111000111110100110100001101000011000001100000011101001011100100001010001011000011000000100 <
1F
#129
0+
b101 3
0F
#130
b01111000 B
1F
#131
b000 3
0F
#132
b00011010 C
1F
#133
1#
b001 3
0F
#134
b00001011 :
b1100 ;
b00001011 E
1F
#135
0#
1$
b010 3
0F
#136
b1011 5
1F
#137
0$
1%
b011 3
0F
#138
b1000 4
b1111 8
b01011000 A
1F
#139
0%
1*
b100 3
0F
b00011010 H
#140
b10111111 6
1F
#141
0*
b00011010 0
b101 3
0F
b00000000 H
#142
1F
#143
b000 3
0F
#144
1F
#145
1#
b001 3
0F
#146
b00001100 :
b1101 ;
b00001100 E
1F
#147
0#
1$
b010 3
0F
#148
b1100 5
1F
#149
0$
1%
b011 3
0F
#150
b1011 4
b01100000 A
1F
#151
0%
1.
b100 3
b00011010 D
0F
#152
b11111111 6
1F
#153
b101 3
0F
#154
1F
#155
b000 3
0F
#156
1F
#157
1#
b001 3
0F
#158
b00001101 :
b1110 ;
b00001101 E
1F
#159
0#
1$
b010 3
0F
#160
b1101 5
1F
#161
0$
1%
b011 3
0F
#162
b1111 4
b01101000 A
1F
#163
0%
0F
#164
b00000000 6
1F
#165
0F
#166
b00000000 B
1F
#167
0F
#168
b00000100 C
1F
