cpuf.v
// LITTLE ENDIAN
// First four bytes are instruction, last four address
// verilator lint_off BLKANDNBLK

// INSTRUCTIONS
// [_ _ _ _][_ _ _ _]
//   Instr.   Addr.
// OP_LDA : 1000 => Load value at address into register A
// OP_LDB : 0100 => Load value at address into register B
// OP_ADD : 0010 => Add values in registers A and B
// OP_SUB : 0001 => Subtract value in Register B from register A
// OP_MUL : 1100 => Mutiply A and B
// OP_DIV : 1010 => Divide A by B
// OP_JMP : 1001 => Jump to instruction at address
// OP_HLT : 1111 => Halt 

// STUFF ON Instruction Bus
module program_counter(inout [7:0] bus_i, input clk, input reset, input pc_a);
    
    reg [3:0] pc;
    
    always @(posedge clk) begin
        if (reset)
            pc <= 0;
        else if (pc_a)
            pc <= pc + 1; 
    end

    assign bus_i = (pc_a) ? {4'bz,pc} : 8'bz;

endmodule

module instruction_register(inout [7:0] bus_i, input [7:0] from_ram, output [3:0] to_ctrl, input clk, input reset, input ir_a);

    reg [3:0] instruction;

    always @(posedge clk) begin
        if (reset)
            instruction <= 0;
        else if (ir_a)
            instruction <= from_ram[7:4]; 
    end

    //assign bus_i = (out_b) ? {instruction,4'bz} : 8'bz;
    assign to_ctrl = (ir_a) ? instruction : 4'bz;

endmodule

module mar(inout [7:0] bus_i, output [3:0] to_ram, input clk, input reset, input mar_a);

    reg [3:0] address;

    always @(posedge clk) begin
        if(reset)
            address <= 0;
        else if (mar_a)
            address <= bus_i[3:0];
    end

    assign to_ram = (mar_a) ? address : 4'bz;

endmodule
// -----

// RAM
module ram(output [7:0] to_ir, inout [7:0] to_a, inout [7:0] to_b, input [3:0] mar_in, input in_b, input out_b, input in_a, input out_a, input clk, input reset);

    reg [128:0] mem;
    reg [7:0] index;
    reg [7:0] out;

    always @(posedge clk) begin
        mem[7:0] <= 8'b00000000;
        mem[15:8] <= 8'b01000001;
        mem[23:16] <= 8'b11111111;
        mem[31:24] <= 8'b00000010;
        mem[39:32] <= 8'b00000001;
        mem[47:40] <= 8'b10001001;
        if(reset) begin
            index <= 0;
            out <= 0;
        end
        else if(in_b) begin
            mem[127:120] <= to_b;
        end
        else if(in_a) begin
            mem[119:112] <= to_a;
        end
        index <= mar_in * 8;
        out <= mem[index +: 8];
    end

    assign to_a = (out_a) ? out : 8'bz;
    assign to_b = (out_b) ? out : 8'bz;
    assign to_ir = out;

endmodule
// Stuff on data bus

module areg(inout [7:0] bus_d, input [7:0] from_ram, input clk, input out_b, input out_a, input active);

    reg [7:0] areg;

    always @(posedge clk) begin
        areg <= from_ram;
    end

    assign bus_d = (out_b) ? areg : 8'bz;


endmodule

module controller(inout [7:0] bus_i, inout [7:0] bus_d, output reg pc_a, output reg mar_a, output reg ir_a, input [3:0] ir_i, input clk, input reset);
    reg [2:0] stagecount = 0;
    reg aflag = 0;

    // CODES

    parameter OP_LDA = 4'b1000;
    parameter OP_LDB = 4'b0100;
    parameter OP_ADD = 4'b0010;
    parameter OP_SUB = 4'b0001;
    parameter OP_MUL = 4'b1100;
    parameter OP_DIV = 4'b1010;
    parameter OP_JMP = 4'b1001;
    parameter OP_HLT = 4'b1111;


    // Control word: pc_a, mar_a, ir_a

    always @(posedge clk) begin
        stagecount = stagecount + 1;
        if (stagecount == 4) begin
            pc_a = 0;
            mar_a = 0;
            ir_a = 0;
            //ctrl_wd = 000;
            stagecount = 0;
        end
        // First 3 stages are always the same
        if (stagecount == 1) begin
            pc_a = 1;
            mar_a = 1;
            ir_a = 0;
            //ctrl_wd = 110;
        end
        if (stagecount == 2) begin
            pc_a = 0;
            mar_a = 1;
            ir_a = 0;
            //ctrl_wd = 010;
        end
        if (stagecount == 3) begin
            pc_a = 0;
            mar_a = 0;
            ir_a = 1;
            //ctrl_wd = 001;
        end
        if (ir_i == OP_LDA) begin
            if (stagecount == 4) begin
            end
        end 


        
    end


endmodule

module top(output [7:0] bus_i, input clk, input reset);
    reg pc_a = 0;
    reg mar_a = 0;
    reg ir_a = 0;
    reg in_b = 0;
    reg out_b = 0;
    reg in_a = 0;
    reg out_a = 0;
    reg [3:0] ir_i;
    reg [7:0] bus_d;
    wire [3:0] to_ram;
    wire [7:0] to_ir;
    wire [7:0] to_a;
    wire [7:0] to_b;

    controller control(.bus_i(bus_i), .bus_d(bus_d), .pc_a(pc_a), .mar_a(mar_a), .ir_a(ir_a), .ir_i(ir_i), .clk(clk), .reset(reset));

    program_counter counter(.bus_i(bus_i), .clk(clk), .reset(reset), .pc_a(pc_a));

    mar mar(.bus_i(bus_i), .to_ram(to_ram), .clk(clk), .reset(reset), .mar_a(mar_a));

    ram ram(.to_ir(to_ir), .to_a(to_a), .to_b(to_b), .mar_in(to_ram), .in_b(in_b), .out_b(out_b), .in_a(in_a), .out_a(out_a), .clk(clk), .reset(reset));

    instruction_register ir(.bus_i(bus_i), .from_ram(to_ir), .to_ctrl(ir_i), .clk(clk), .reset(reset), .ir_a(ir_a));


endmodule

Waveform.vcd
$version Generated by VerilatedVcd $end
$timescale 1ps $end

 $scope module TOP $end
  $var wire  8 4 bus_i [7:0] $end
  $var wire  1 5 clk $end
  $var wire  1 6 reset $end
  $scope module top $end
   $var wire  8 8 bus_d [7:0] $end
   $var wire  8 4 bus_i [7:0] $end
   $var wire  1 5 clk $end
   $var wire  1 7 in_a $end
   $var wire  1 7 in_b $end
   $var wire  1 % ir_a $end
   $var wire  4 & ir_i [3:0] $end
   $var wire  1 $ mar_a $end
   $var wire  1 7 out_a $end
   $var wire  1 7 out_b $end
   $var wire  1 # pc_a $end
   $var wire  1 6 reset $end
   $var wire  8 9 to_a [7:0] $end
   $var wire  8 9 to_b [7:0] $end
   $var wire  8 ( to_ir [7:0] $end
   $var wire  4 ' to_ram [3:0] $end
   $scope module control $end
    $var wire  4 < OP_ADD [3:0] $end
    $var wire  4 ? OP_DIV [3:0] $end
    $var wire  4 A OP_HLT [3:0] $end
    $var wire  4 @ OP_JMP [3:0] $end
    $var wire  4 : OP_LDA [3:0] $end
    $var wire  4 ; OP_LDB [3:0] $end
    $var wire  4 > OP_MUL [3:0] $end
    $var wire  4 = OP_SUB [3:0] $end
    $var wire  1 * aflag $end
    $var wire  8 8 bus_d [7:0] $end
    $var wire  8 4 bus_i [7:0] $end
    $var wire  1 5 clk $end
    $var wire  1 % ir_a $end
    $var wire  4 & ir_i [3:0] $end
    $var wire  1 $ mar_a $end
    $var wire  1 # pc_a $end
    $var wire  1 6 reset $end
    $var wire  3 ) stagecount [2:0] $end
   $upscope $end
   $scope module counter $end
    $var wire  8 4 bus_i [7:0] $end
    $var wire  1 5 clk $end
    $var wire  4 + pc [3:0] $end
    $var wire  1 # pc_a $end
    $var wire  1 6 reset $end
   $upscope $end
   $scope module ir $end
    $var wire  8 4 bus_i [7:0] $end
    $var wire  1 5 clk $end
    $var wire  8 ( from_ram [7:0] $end
    $var wire  4 , instruction [3:0] $end
    $var wire  1 % ir_a $end
    $var wire  1 6 reset $end
    $var wire  4 & to_ctrl [3:0] $end
   $upscope $end
   $scope module mar $end
    $var wire  4 - address [3:0] $end
    $var wire  8 4 bus_i [7:0] $end
    $var wire  1 5 clk $end
    $var wire  1 $ mar_a $end
    $var wire  1 6 reset $end
    $var wire  4 ' to_ram [3:0] $end
   $upscope $end
   $scope module ram $end
    $var wire  1 5 clk $end
    $var wire  1 7 in_a $end
    $var wire  1 7 in_b $end
    $var wire  8 3 index [7:0] $end
    $var wire  4 ' mar_in [3:0] $end
    $var wire 129 . mem [128:0] $end
    $var wire  8 ( out [7:0] $end
    $var wire  1 7 out_a $end
    $var wire  1 7 out_b $end
    $var wire  1 6 reset $end
    $var wire  8 9 to_a [7:0] $end
    $var wire  8 9 to_b [7:0] $end
    $var wire  8 ( to_ir [7:0] $end
   $upscope $end
  $upscope $end
 $upscope $end
$enddefinitions $end


#0
0#
0$
0%
b0000 &
b0000 '
b00000000 (
b000 )
0*
b0000 +
b0000 ,
b0000 -
b000000000000000000000000000000000000000000000000000000000000000000000000000000000000000000000000000000000000000000000000000000000 .
b00000000 3
b00000000 4
15
06
07
b00000000 8
b00000000 9
b1000 :
b0100 ;
b0010 <
b0001 =
b1100 >
b1010 ?
b1001 @
b1111 A
#1
05
#2
1#
1$
b001 )
b0001 +
b000000000000000000000000000000000000000000000000000000000000000000000000000000000100010010000000100000010111111110100000100000000 .
b00000001 4
15
#3
05
#4
0#
b0001 '
b010 )
b0001 -
b00000000 4
15
#5
05
#6
0$
1%
b0000 '
b011 )
15
#7
05
#8
0%
b000 )
15
#9
05
#10
1#
1$
b001 )
b0010 +
b0000 -
b00001000 3
b00000010 4
15
#11
05
#12
0#
b0010 '
b01000001 (
b010 )
b0010 -
b00000000 3
b00000000 4
15
#13
05
#14
0$
1%
b0100 &
b0000 '
b00000000 (
b011 )
b0100 ,
15
#15
05
#16
0%
b0000 &
b000 )
15
#17
05
#18
1#
1$
b001 )
b0011 +
b0000 -
b00010000 3
b00000011 4
15
#19
05
#20
0#
b0011 '
b11111111 (
b010 )
b0011 -
b00000000 3
b00000000 4
15
#21
05
#22
0$
1%
b1111 &
b0000 '
b00000000 (
b011 )
b1111 ,
15
#23
05
#24
0%
b0000 &
b000 )
15
#25
05
#26
1#
1$
b001 )
b0100 +
b0000 -
b00011000 3
b00000100 4
15
#27
05
#28
0#
b0100 '
b00000010 (
b010 )
b0100 -
b00000000 3
b00000000 4
15
#29
05
#30
0$
1%
b0000 '
b00000000 (
b011 )
b0000 ,
15
#31
05
#32
0%
b000 )
15
#33
05
#34
1#
1$
b001 )
b0101 +
b0000 -
b00100000 3
b00000101 4
15
#35
05
#36
0#
b0101 '
b00000001 (
b010 )
b0101 -
b00000000 3
b00000000 4
15
#37
05
#38
0$
1%
b0000 '
b00000000 (
b011 )
15
#39
05
#40
0%
b000 )
15
#41
05
#42
1#
1$
b001 )
b0110 +
b0000 -
b00101000 3
b00000110 4
15
#43
05
#44
0#
b0110 '
b10001001 (
b010 )
b0110 -
b00000000 3
b00000000 4
15
#45
05
#46
0$
1%
b1000 &
b0000 '
b00000000 (
b011 )
b1000 ,
15
#47
05
#48
0%
b0000 &
b000 )
15
#49
05
#50
1#
1$
b001 )
b0111 +
b0000 -
b00110000 3
b00000111 4
15
#51
05
#52
0#
b0111 '
b010 )
b0111 -
b00000000 3
b00000000 4
15
#53
05
#54
0$
1%
b0000 '
b011 )
1*
b0000 ,
15
#55
05
#56
0%
b000 )
15
#57
05
#58
1#
1$
b001 )
b1000 +
b0000 -
b00111000 3
b00001000 4
15
#59
05
#60
0#
b1000 '
b010 )
b1000 -
b00000000 3
b00000000 4
15
#61
05
#62
0$
1%
b0000 '
b011 )
15
#63
05
#64
0%
b000 )
15
#65
05
#66
1#
1$
b001 )
b1001 +
b0000 -
b01000000 3
b00001001 4
15
#67
05
#68
0#
b1001 '
b010 )
b1001 -
b00000000 3
b00000000 4
15
#69
05
#70
0$
1%
b0000 '
b011 )
15
#71
05
#72
0%
b000 )
15
#73
05
#74
1#
1$
b001 )
b1010 +
b0000 -
b01001000 3
b00001010 4
15
#75
05
#76
0#
b1010 '
b010 )
b1010 -
b00000000 3
b00000000 4
15
#77
05
#78
0$
1%
b0000 '
b011 )
15
#79
05
#80
0%
b000 )
15
#81
05
#82
1#
1$
b001 )
b1011 +
b0000 -
b01010000 3
b00001011 4
15
#83
05
#84
0#
b1011 '
b010 )
b1011 -
b00000000 3
b00000000 4
15
#85
05
#86
0$
1%
b0000 '
b011 )
15
#87
05
#88
0%
b000 )
15
#89
05
#90
1#
1$
b001 )
b1100 +
b0000 -
b01011000 3
b00001100 4
15
#91
05
#92
0#
b1100 '
b010 )
b1100 -
b00000000 3
b00000000 4
15
#93
05
#94
0$
1%
b0000 '
b011 )
15
#95
05
#96
0%
b000 )
15
#97
05
#98
1#
1$
b001 )
b1101 +
b0000 -
b01100000 3
b00001101 4
15
