cpuf.v
// LITTLE ENDIAN
// First four bytes are instruction, last four address
// verilator lint_off BLKANDNBLK

// INSTRUCTIONS
// [_ _ _ _][_ _ _ _]
//   Instr.   Addr.
// OP_LDA : 1000 => Load value at address into register A
// OP_LDB : 0100 => Load value at address into register B
// OP_ADD : 0010 => Add values in Register A and B and dump in accumulator
// OP_SUB : 0001 => Subtract value in B from register A and dump in accumulator
// OP_JMP : 1001 => Jump to instruction at address
// OP_HLT : 1111 => Halt 

// STUFF ON Instruction Bus
module program_counter(inout [7:0] bus_i, input clk, input reset, input pc_a);
    
    reg [3:0] pc;
    
    always @(posedge clk) begin
        if (reset)
            pc <= 0;
        else if (pc_a)
            pc <= pc + 1; 
    end

    assign bus_i = (pc_a) ? {4'bz,pc} : 8'bz;

endmodule

module instruction_register(inout [7:0] bus_i, input [7:0] from_ram, output [3:0] to_ctrl, output [3:0] to_ram, input clk, input reset, input ir_a);

    reg [3:0] instruction;
    reg [3:0] address; // Address in instruction

    always @(posedge clk) begin
        if (reset) begin
            instruction <= 0;
        end
        else if (ir_a) begin
            address <= from_ram[3:0];
            instruction <= from_ram[7:4];
        end 
    end

    //assign bus_i = (out_b) ? {instruction,4'bz} : 8'bz;
    assign to_ctrl = (1) ? instruction : 4'bz;
    assign to_ram = address;

endmodule

module mar(inout [7:0] bus_i, output [3:0] to_ram, input [3:0] from_ir, input clk, input reset, input mar_a);

    reg [3:0] address;

    always @(posedge clk) begin
        if (mar_a)
            address <= bus_i[3:0];
        //else
        //    address <= from_ir;
    end

    //assign to_ram = (mar_a) ? address : 4'bz;
    assign to_ram = address;
endmodule
// -----

// RAM
module ram(output [7:0] to_ir, inout [7:0] to_a, inout [7:0] to_b, input [3:0] mar_in, input [3:0] address_ir, input in_b, input out_b, input in_a, input out_a, input clk, input reset);

    reg [128:0] mem;
    reg [7:0] index_ir;
    reg [7:0] index_reg;
    reg [7:0] out_reg;
    reg [7:0] out_ir;

    always @(posedge clk) begin
        mem[7:0] <= 8'b00000100;
        mem[15:8] <= 8'b10000101;
        mem[23:16] <= 8'b01000110;
        mem[31:24] <= 8'b00101111;
        mem[39:32] <= 8'b00001100;
        mem[47:40] <= 8'b00001110;
        
        if(reset) begin
            //index <= 0;
            //out <= 0;
        end
        else if(in_b) begin
            mem[127:120] <= to_b;
        end
        else if(in_a) begin
            mem[119:112] <= to_a;
        end
        index_ir <= mar_in * 8;
        index_reg <= address_ir * 8;
        out_reg <= mem[index_reg +: 8];
        out_ir <= mem[index_ir +: 8];
    end

    assign to_a = (out_a) ? out_reg : 8'bz;
    assign to_b = (out_b) ? out_reg : 8'bz;
    assign to_ir = out_ir;

endmodule
// Stuff on data bus

module register(output [7:0] to_c, inout [7:0] bus_d, input [7:0] from_ram, input clk, input ram_in, input out_b);

    reg [7:0] areg;

    always @(negedge clk) begin
        if (ram_in)
            areg <= from_ram;
    end

    assign bus_d = (out_b) ? areg : 8'bz;
    assign to_c = areg;


endmodule

module alu(output reg [7:0] to_acc, inout [7:0] bus_d, input [7:0] from_a, input [7:0] from_b, input clk, input ad, input sub);
    reg [7:0] out;
    
    always @(posedge clk) begin
        if(ad)
            out <= from_a + from_b;
        if(sub)
            out <= from_a - from_b;
    
    assign to_acc = (1) ? out : 8'bz; //ad || sub

    end

endmodule

module controller(inout [7:0] bus_i, inout [7:0] bus_d, output reg pc_a, output reg mar_a, output reg ir_a, output reg in_a, output reg out_a, output reg in_b, output reg out_b, output reg ad, output reg sb, input [3:0] ir_i, input clk, input reset);
    reg [2:0] stagecount = 0;
    reg aflag = 0;

    // CODES

    parameter OP_LDA = 4'b1000;
    parameter OP_LDB = 4'b0100;
    parameter OP_ADD = 4'b0010;
    parameter OP_SUB = 4'b0001;
    parameter OP_MUL = 4'b1100;
    parameter OP_DIV = 4'b1010;
    parameter OP_JMP = 4'b1001;
    parameter OP_HLT = 4'b1111;


    // Control word: pc_a, mar_a, ir_a, in_a (input to ram), out_a (output from ram), in_b, out_b, ad, sb

    always @(posedge clk) begin
        stagecount = stagecount + 1;
        if (stagecount == 6) begin
            pc_a = 0;
            mar_a = 0;
            ir_a = 0;
            in_a = 0;
            out_a = 0;
            in_b = 0;
            out_b = 0;
            ad = 0;
            sb = 0;
            //ctrl_wd = 000;
            stagecount = 0;
        end
        // First 3 stages are always the same
        if (stagecount == 1) begin
            pc_a = 1;
            mar_a = 0;
            ir_a = 0;
            in_a = 0;
            out_a = 0;
            in_b = 0;
            out_b = 0;
            ad = 0;
            sb = 0;
            //ctrl_wd = 110;
        end
        if (stagecount == 2) begin
            pc_a = 0;
            mar_a = 1;
            ir_a = 0; //0
            in_a = 0;
            out_a = 0;
            in_b = 0;
            out_b = 0;
            //ctrl_wd = 010;
        end
        if (stagecount == 3) begin
            pc_a = 0;
            mar_a = 0;
            ir_a = 1; //1
            in_a = 0;
            out_a = 0;
            in_b = 0;
            out_b = 0;
            ad = 0;
            sb = 0;
            //ctrl_wd = 001;
        end
        if (ir_i == OP_LDA) begin
            if (stagecount == 4) begin
                pc_a = 0;
                mar_a = 0;
                ir_a = 0;
                in_a = 0;
                out_a = 1;
                in_b = 0;
                out_b = 0;
                ad = 0;
                sb = 0;
            end
            if (stagecount == 5) begin
                pc_a = 0;
                mar_a = 0;
                ir_a = 0;
                in_a = 0;
                out_a = 0;
                in_b = 0;
                out_b = 0;
                ad = 0;
                sb = 0;
            end
        end 
        else if (ir_i == OP_LDB) begin
            if (stagecount == 4) begin
                pc_a = 0;
                mar_a = 0;
                ir_a = 0;
                in_a = 0;
                out_a = 0;
                in_b = 0;
                out_b = 1;
                ad = 0;
                sb = 0;
            end
            if (stagecount == 5) begin
                pc_a = 0;
                mar_a = 0;
                ir_a = 0;
                in_a = 0;
                out_a = 0;
                in_b = 0;
                out_b = 0;
                ad = 0;
                sb = 0;
            end
        end
        else if (ir_i == OP_ADD) begin
            if (stagecount == 4) begin
                pc_a = 0;
                mar_a = 0;
                ir_a = 0;
                in_a = 0;
                out_a = 0;
                in_b = 0;
                out_b = 0;
                ad = 1;
                sb = 0;
            end
            if (stagecount == 5) begin
                pc_a = 0;
                mar_a = 0;
                ir_a = 0;
                in_a = 0;
                out_a = 0;
                in_b = 0;
                out_b = 0;
                ad = 0;
                sb = 0;
            end
        end
        else if (ir_i == OP_SUB) begin
            if (stagecount == 4) begin
                pc_a = 0;
                mar_a = 0;
                ir_a = 0;
                in_a = 0;
                out_a = 0;
                in_b = 0;
                out_b = 0;
                ad = 0;
                sb = 1;
            end
            if (stagecount == 5) begin
                pc_a = 0;
                mar_a = 0;
                ir_a = 0;
                in_a = 0;
                out_a = 0;
                in_b = 0;
                out_b = 0;
                ad = 0;
                sb = 0;
            end
        end
        else begin
            if (stagecount == 4) begin
                pc_a = 0;
                mar_a = 0;
                ir_a = 0;
                in_a = 0;
                out_a = 0;
                in_b = 0;
                out_b = 0;
                ad = 0;
                sb = 0;
            end
            if (stagecount == 5) begin
                pc_a = 0;
                mar_a = 0;
                ir_a = 0;
                in_a = 0;
                out_a = 0;
                in_b = 0;
                out_b = 0;
                ad = 0;
                sb = 0;
            end
        end


        
    end


endmodule

module top(output [7:0] bus_i, input clk, input reset);
    reg pc_a = 0;
    reg mar_a = 0;
    reg ir_a = 0;
    // RAM flags
    reg in_b = 0;
    reg out_b = 0;
    reg in_a = 0;
    reg out_a = 0;
    //-----
    // accumulator
    reg c_out_acc = 1;
    reg c_out = 0;
    reg ad = 0;
    reg sb = 0;
    // Register flags (BUS OUT)
    reg a_out = 0;
    reg b_out = 0;
    //----
    reg out_bus = 0;
    reg [3:0] ir_i;
    reg [7:0] bus_d;
    wire [3:0] to_ram;
    wire [7:0] to_ir;
    wire [7:0] to_a;
    wire [7:0] to_b;
    wire [7:0] to_acc;
    wire [7:0] a_calc;
    wire [7:0] b_calc;
    wire [7:0] c_calc;
    wire [3:0] address_ir;

    controller control(.bus_i(bus_i), .bus_d(bus_d), .pc_a(pc_a), .mar_a(mar_a), .ir_a(ir_a), .in_a(in_a), .out_a(out_a), .in_b(in_b), .out_b(out_b), .ad(ad), .sb(sb), .ir_i(ir_i), .clk(clk), .reset(reset));

    program_counter counter(.bus_i(bus_i), .clk(clk), .reset(reset), .pc_a(pc_a));

    mar mar(.bus_i(bus_i), .to_ram(to_ram), .from_ir(address_ir), .clk(clk), .reset(reset), .mar_a(mar_a));

    ram ram(.to_ir(to_ir), .to_a(to_a), .to_b(to_b), .mar_in(to_ram), .address_ir(address_ir), .in_b(in_b), .out_b(out_b), .in_a(in_a), .out_a(out_a), .clk(clk), .reset(reset));

    instruction_register ir(.bus_i(bus_i), .from_ram(to_ir), .to_ctrl(ir_i), .to_ram(address_ir), .clk(clk), .reset(reset), .ir_a(ir_a));

    register areg(.to_c(a_calc), .bus_d(bus_d), .from_ram(to_a), .clk(clk), .ram_in(out_a), .out_b(a_out));
    
    register breg(.to_c(b_calc), .bus_d(bus_d), .from_ram(to_b), .clk(clk), .ram_in(out_b), .out_b(b_out));

    // Here from ram is from alu, too lazy to modify names
    register accumulator(.to_c(c_calc), .bus_d(bus_d), .from_ram(to_acc), .clk(clk), .ram_in(c_out_acc), .out_b(c_out));

    alu alu(.to_acc(to_acc), .bus_d(bus_d), .from_a(a_calc), .from_b(b_calc), .clk(clk), .ad(ad), .sub(sb));



endmodule

Waveform.vcd
$version Generated by VerilatedVcd $end
$timescale 1ps $end

 $scope module TOP $end
  $var wire  8 A bus_i [7:0] $end
  $var wire  1 B clk $end
  $var wire  1 C reset $end
  $scope module top $end
   $var wire  8 > a_calc [7:0] $end
   $var wire  1 E a_out $end
   $var wire  1 * ad $end
   $var wire  4 2 address_ir [3:0] $end
   $var wire  8 ? b_calc [7:0] $end
   $var wire  1 E b_out $end
   $var wire  8 F bus_d [7:0] $end
   $var wire  8 A bus_i [7:0] $end
   $var wire  8 @ c_calc [7:0] $end
   $var wire  1 E c_out $end
   $var wire  1 D c_out_acc $end
   $var wire  1 B clk $end
   $var wire  1 ( in_a $end
   $var wire  1 & in_b $end
   $var wire  1 % ir_a $end
   $var wire  4 , ir_i [3:0] $end
   $var wire  1 $ mar_a $end
   $var wire  1 ) out_a $end
   $var wire  1 ' out_b $end
   $var wire  1 E out_bus $end
   $var wire  1 # pc_a $end
   $var wire  1 C reset $end
   $var wire  1 + sb $end
   $var wire  8 / to_a [7:0] $end
   $var wire  8 1 to_acc [7:0] $end
   $var wire  8 0 to_b [7:0] $end
   $var wire  8 . to_ir [7:0] $end
   $var wire  4 - to_ram [3:0] $end
   $scope module accumulator $end
    $var wire  8 @ areg [7:0] $end
    $var wire  8 F bus_d [7:0] $end
    $var wire  1 B clk $end
    $var wire  8 1 from_ram [7:0] $end
    $var wire  1 E out_b $end
    $var wire  1 D ram_in $end
    $var wire  8 @ to_c [7:0] $end
   $upscope $end
   $scope module alu $end
    $var wire  1 * ad $end
    $var wire  8 F bus_d [7:0] $end
    $var wire  1 B clk $end
    $var wire  8 > from_a [7:0] $end
    $var wire  8 ? from_b [7:0] $end
    $var wire  8 3 out [7:0] $end
    $var wire  1 + sub $end
    $var wire  8 1 to_acc [7:0] $end
   $upscope $end
   $scope module areg $end
    $var wire  8 > areg [7:0] $end
    $var wire  8 F bus_d [7:0] $end
    $var wire  1 B clk $end
    $var wire  8 / from_ram [7:0] $end
    $var wire  1 E out_b $end
    $var wire  1 ) ram_in $end
    $var wire  8 > to_c [7:0] $end
   $upscope $end
   $scope module breg $end
    $var wire  8 ? areg [7:0] $end
    $var wire  8 F bus_d [7:0] $end
    $var wire  1 B clk $end
    $var wire  8 0 from_ram [7:0] $end
    $var wire  1 E out_b $end
    $var wire  1 ' ram_in $end
    $var wire  8 ? to_c [7:0] $end
   $upscope $end
   $scope module control $end
    $var wire  4 I OP_ADD [3:0] $end
    $var wire  4 L OP_DIV [3:0] $end
    $var wire  4 N OP_HLT [3:0] $end
    $var wire  4 M OP_JMP [3:0] $end
    $var wire  4 G OP_LDA [3:0] $end
    $var wire  4 H OP_LDB [3:0] $end
    $var wire  4 K OP_MUL [3:0] $end
    $var wire  4 J OP_SUB [3:0] $end
    $var wire  1 * ad $end
    $var wire  1 E aflag $end
    $var wire  8 F bus_d [7:0] $end
    $var wire  8 A bus_i [7:0] $end
    $var wire  1 B clk $end
    $var wire  1 ( in_a $end
    $var wire  1 & in_b $end
    $var wire  1 % ir_a $end
    $var wire  4 , ir_i [3:0] $end
    $var wire  1 $ mar_a $end
    $var wire  1 ) out_a $end
    $var wire  1 ' out_b $end
    $var wire  1 # pc_a $end
    $var wire  1 C reset $end
    $var wire  1 + sb $end
    $var wire  3 4 stagecount [2:0] $end
   $upscope $end
   $scope module counter $end
    $var wire  8 A bus_i [7:0] $end
    $var wire  1 B clk $end
    $var wire  4 5 pc [3:0] $end
    $var wire  1 # pc_a $end
    $var wire  1 C reset $end
   $upscope $end
   $scope module ir $end
    $var wire  4 2 address [3:0] $end
    $var wire  8 A bus_i [7:0] $end
    $var wire  1 B clk $end
    $var wire  8 . from_ram [7:0] $end
    $var wire  4 , instruction [3:0] $end
    $var wire  1 % ir_a $end
    $var wire  1 C reset $end
    $var wire  4 , to_ctrl [3:0] $end
    $var wire  4 2 to_ram [3:0] $end
   $upscope $end
   $scope module mar $end
    $var wire  4 - address [3:0] $end
    $var wire  8 A bus_i [7:0] $end
    $var wire  1 B clk $end
    $var wire  4 2 from_ir [3:0] $end
    $var wire  1 $ mar_a $end
    $var wire  1 C reset $end
    $var wire  4 - to_ram [3:0] $end
   $upscope $end
   $scope module ram $end
    $var wire  4 2 address_ir [3:0] $end
    $var wire  1 B clk $end
    $var wire  1 ( in_a $end
    $var wire  1 & in_b $end
    $var wire  8 ; index_ir [7:0] $end
    $var wire  8 < index_reg [7:0] $end
    $var wire  4 - mar_in [3:0] $end
    $var wire 129 6 mem [128:0] $end
    $var wire  1 ) out_a $end
    $var wire  1 ' out_b $end
    $var wire  8 . out_ir [7:0] $end
    $var wire  8 = out_reg [7:0] $end
    $var wire  1 C reset $end
    $var wire  8 / to_a [7:0] $end
    $var wire  8 0 to_b [7:0] $end
    $var wire  8 . to_ir [7:0] $end
   $upscope $end
  $upscope $end
 $upscope $end
$enddefinitions $end


#0
0#
0$
0%
0&
0'
0(
0)
0*
0+
b0000 ,
b0000 -
b00000000 .
b00000000 /
b00000000 0
b00000000 1
b0000 2
b00000000 3
b000 4
b0000 5
b000000000000000000000000000000000000000000000000000000000000000000000000000000000000000000000000000000000000000000000000000000000 6
b00000000 ;
b00000000 <
b00000000 =
b00000000 >
b00000000 ?
b00000000 @
b00000000 A
1B
0C
1D
0E
b00000000 F
b1000 G
b0100 H
b0010 I
b0001 J
b1100 K
b1010 L
b1001 M
b1111 N
#1
0B
#2
1#
b001 4
b0001 5
b000000000000000000000000000000000000000000000000000000000000000000000000000000000000011100000110000101111010001101000010100000100 6
b00000001 A
1B
#3
0B
#4
0#
1$
b0001 -
b00000100 .
b010 4
b00000100 =
b00000000 A
1B
#5
0B
#6
0$
1%
b0100 2
b011 4
b00001000 ;
1B
#7
0B
#8
0%
b10000101 .
b100 4
b00100000 <
1B
#9
0B
#10
b101 4
b00001100 =
1B
#11
0B
#12
b000 4
1B
#13
0B
#14
1#
b001 4
b0010 5
b00000010 A
1B
#15
0B
#16
0#
1$
b0010 -
b010 4
b00000000 A
1B
#17
0B
#18
0$
1%
b1000 ,
b0101 2
b011 4
b00010000 ;
1B
#19
0B
#20
0%
1)
b01000110 .
b00001100 /
b100 4
b00101000 <
1B
#21
b00001100 >
0B
#22
0)
b00000000 /
b101 4
b00001110 =
1B
#23
0B
#24
b000 4
1B
#25
0B
#26
1#
b001 4
b0011 5
b00000011 A
1B
#27
0B
#28
0#
1$
b0011 -
b010 4
b00000000 A
1B
#29
0B
#30
0$
1%
b0100 ,
b0110 2
b011 4
b00011000 ;
1B
#31
0B
#32
0%
1'
b00101111 .
b00001110 0
b100 4
b00110000 <
1B
#33
b00001110 ?
0B
#34
0'
b00000000 0
b101 4
b00000000 =
1B
#35
0B
#36
b000 4
1B
#37
0B
#38
1#
b001 4
b0100 5
b00000100 A
1B
#39
0B
#40
0#
1$
b0100 -
b010 4
b00000000 A
1B
#41
0B
#42
0$
1%
b0010 ,
b1111 2
b011 4
b00100000 ;
1B
#43
0B
#44
0%
1*
b00001100 .
b00011010 3
b100 4
b01111000 <
1B
#45
0B
#46
0*
b00011010 1
b101 4
1B
#47
b00011010 @
0B
#48
b000 4
1B
#49
0B
#50
1#
b001 4
b0101 5
b00000101 A
1B
#51
0B
#52
0#
1$
b0101 -
b010 4
b00000000 A
1B
#53
0B
#54
0$
1%
b0000 ,
b1100 2
b011 4
b00101000 ;
1B
#55
0B
#56
0%
b00001110 .
b100 4
b01100000 <
1B
#57
0B
#58
b101 4
1B
#59
0B
#60
b000 4
1B
#61
0B
#62
1#
b001 4
b0110 5
b00000110 A
1B
#63
0B
#64
0#
1$
b0110 -
b010 4
b00000000 A
1B
#65
0B
#66
0$
1%
b1110 2
b011 4
b00110000 ;
1B
#67
0B
#68
0%
b00000000 .
b100 4
b01110000 <
1B
#69
0B
#70
b101 4
1B
#71
0B
#72
b000 4
1B
#73
0B
#74
1#
b001 4
b0111 5
b00000111 A
1B
#75
0B
#76
0#
1$
b0111 -
b010 4
b00000000 A
1B
#77
0B
#78
0$
1%
b0000 2
b011 4
b00111000 ;
1B
#79
0B
#80
0%
b100 4
b00000000 <
1B
#81
0B
#82
b101 4
b00000100 =
1B
#83
0B
#84
b000 4
1B
#85
0B
#86
1#
b001 4
b1000 5
b00001000 A
1B
#87
0B
#88
0#
1$
b1000 -
b010 4
b00000000 A
1B
#89
0B
#90
0$
1%
b011 4
b01000000 ;
1B
#91
0B
#92
0%
b100 4
1B
#93
0B
#94
b101 4
1B
#95
0B
#96
b000 4
1B
#97
0B
#98
1#
b001 4
b1001 5
b00001001 A
1B
